Workbook

Sheet All_Data
A1: Meta Data | H1: Dataset Information | V1: HAR Algorithm/Model Information and Preprocessing Steps | AJ1: Availability
A2: Contribution Area | B2: Article ID | C2: Title | D2: First Author | E2: doi | F2: Date (Month) | G2: Date (Year) | H2: Dataset Name | I2: Data Public? | J2: Dataset Link (if self collected) | K2: Frequency (Hz) | L2: Range (± g) | M2: Device (Name + Brand) | N2: No. Participants | O2: Demographics | P2: Collection Protocol | Q2: Balanced? | R2: No. Activities | S2: Activity Names | T2: Activitiy Definitions | U2: Sensor Location | V2: Base Algorithm or Architecture | W2: Compare Mult. Algs? | X2: Implementation (software/libraries) | Y2: Hand Crafted Features? | Z2: Features | AA2: Window length (s) | AB2: Overlap (%) | AC2: Train/Test Split | AD2: Metrics | AE2: Performance of Wrist Accel Only (See…) | AF2: Class Wise Evaluation | AG2: Performance of Other Sensors (same dataset) | AH2: Performance of same Algorithm on Other Datasets (not neccesarily WAO) | AI2: Trained on a dataset and evaluated on another one | AJ2: Code? | AK2: Code (Link) | AL2: Trained Model Weights (open weight) | AM2: Replicable? | AN2: Why not replicable? (Defs in Sec. 4.3.1) | AO2: Notes on replication | AP2: Reproducible? | AQ2: Why not reproducible? (Defs in Sec. 4.3.1) | AR2: Notes on reproduction
A3: Algorithm Improvement (e.g., architecture or preprocessing) | B3: 66 | C3: A Hybrid Solution for Human Activity Recognition: Application to Wrist-Worn Accelerometry | D3: Manuel Abbas | E3: https://doi.org/10.1109/ICABME47164.2019.8940233 | F3: Oct | G3: 2019 | H3: SC | I3: N/A | K3: 238 | L3: 8 | M3: LSM9DS1 by STMicroelectronics | N3: 10 | O3: 5 M, 5 F, 22-53 yo | P3: Semi- or highly-supervised | Q3: N | R3: 5 | S3: sitting, standing, walking, jogging, stairs | T3: activities derived from (1) walking towards a chair then sitting down, (2) sitting-down after being inactive for a while, (3) standing-up and staying inactive for a while, (4) standing-up then starting walking immediately. | U3: N/A | V3: Linear and quadratic SVM, Random Forest, Artificial Neural Network (ANN) with one hidden layer of 10 neurons (shallow learning) and k-NN (k=5). | W3: Y | X3: N/A | Y3: Y | Z3: See Section III A | AA3: 5 | AB3: 40 | AC3: 10-fold CV | AD3: Accuracy | AE3: Table 1 | AF3: Y | AG3: N | AH3: N | AI3: N | AJ3: N | AL3: N | AM3: N | AN3: IP | AP3: N | AQ3: DNA | AS3: =IF(AND(AP3="N", ISBLANK(AQ3)), "THIS", "") | AU3: Y | AV3: DNA | AW3: IP
B4: 94 | C4: Characterizing Peaks in Acceleration Signals–Application to Physical Activity Detection Using Wearable Sensors | D4: Manuel Abbas | E4: https://doi.org/10.1109/JSEN.2020.3000394 | F4: Jun | G4: 2020 | H4: SC | I4: N/A | K4: 238 | L4: 8 | M4: LSDM9DS1 | N4: 9 | O4: 4 M, 5 F, 24-53 yo (median of 33 yo), 48-80 kg, 158-180 cm | P4: N/A | Q4: N | R4: 4 | S4: C-1, C-2, C-3, C-4 | T4: clapping hands (C-1), waving goodbye, shaking hands (C-2), walking slowly/quickly, going upstairs then downstairs (C-3) and jogging (C-4) | U4: N/A | V4: RF, CNN, their solution (DT + SVM) | W4: Y | X4: N/A | Y4: Y | Z4: "prominence, width, variability and entropy " or "mean, std, skewness, kurtosis, energy of the signal, frequency-domain entropy, interquartile range, root mean square and mean absolute deviation" | AA4: 3 | AB4: 66 | AC4: 10-fold and LOSO CV | AD4: Accuracy | AE4: Table 2 | AF4: Y | AG4: N | AH4: N | AI4: N | AJ4: N | AL4: N | AM4: Y | AP4: N | AQ4: DNA | AS4: =IF(AND(AP4="N", ISBLANK(AQ4)), "THIS", "") | AU4: N | AV4: TTS | AW4: IF
B5: 5 | C5: Daily living activity recognition based on statistical feature quality group selection | D5: Oresti Banos | E5: https://doi.org/10.1016/j.eswa.2012.01.164 | F5: Jul | G5: 2012 | H5: Bao + Intille | I5: Y | K5: 20 | L5: N/A | M5: N/A | N5: N/A | O5: N/A | P5: Semi- or highly-supervised | Q5: N/A | R5: 4 | S5: Walking, sitting and relaxing, standing still and running | T5: N/A | U5: N/A | V5: C4.5 (DT), SVM with RBF kernel, NB | W5: Y | X5: N/A | Y5: Y | Z5: See Sec. 2.2 and 2.3 | AA5: N/A | AB5: N/A | AC5: 10-fold CV | AD5: Accuracy | AE5: Figure 5 | AF5: N | AG5: Y | AH5: Y* (lab + simfl within a single dataset) | AI5: N | AJ5: N | AL5: N | AM5: N | AN5: IS | AP5: N | AQ5: TTS | AS5: =IF(AND(AP5="N", ISBLANK(AQ5)), "THIS", "") | AV5: ANR | AW5: IS
B6: 24 | C6: Significant Features for Human Activity Recognition Using Tri-Axial Accelerometers | D6: Mohamed Bennasar | E6: https://doi.org/10.3390/s22197482 | F6: Oct | G6: 2022 | H6: HHAR | I6: Y | K6: 100, 200 | L6: N/A | M6: Samsung and LG smartwatch | N6: 9 | O6: 25-30 yo | P6: Semi- or highly-supervised | Q6: N | R6: 6 | S6: walking, biking, sitting, ascending stairs, descending stairs and standing | T6: N/A | U6: N/A | V6: SVM (linear kernel), KNN (k=3) | W6: Y | X6: MATLAB | Y6: Y | Z6: See Table 2 | AA6: 2.5 | AB6: N/A | AC6: 5-fold CV | AD6: Accuracy, F1 | AE6: Table 2, 3, 4 | AF6: N | AG6: N | AH6: Y | AI6: N | AJ6: N | AL6: N | AM6: N | AN6: IS | AP6: N | AQ6: TTS | AS6: =IF(AND(AP6="N", ISBLANK(AQ6)), "THIS", "")
H7: PAMAP2 | I7: Y | K7: 100 | L7: N/A | M7: N/A | N7: 9 | O7: 1F, 8M, 24-32 yo | P7: Semi- or highly-supervised | Q7: N | R7: 12 | S7: Lying (6.7%), Sitting (13.06%), Walking (8.2%), Running (3.3%), Cycling (5.73%), Nordic walking (6.48%), Upstairs (4.08%), Downstairs (3.65), vacuum cleaning (6.13%), Ironing (8.31%), Rope jumping (1.92%), Other (transient activities) (32.44%) | T7: N/A | U7: D | AS7: =IF(AND(AP7="N", ISBLANK(AQ7)), "THIS", "")
B8: 25 | C8: Improving Deep Learning for HAR with Shallow LSTMs | D8: Marius Bock | E8: https://doi.org/10.1145/3460421.3480419 | F8: Sep | G8: 2021 | H8: HHAR | I8: Y | K8: 100 | L8: N/A | M8: N/A | N8: 9 | O8: N/A | P8: N/A | Q8: N/A | R8: 6 | S8: Biking, sitting, standing, walking, walking upstairs and downstairs, (null) | T8: N/A | U8: N/A | V8: LSTMS (1 or 2 layered) | W8: Y | X8: PyTorch | Y8: N | AA8: 1 | AB8: 60 | AC8: LOSO CV | AD8: F1, Precision, Recall | AE8: Fig. 2B | AF8: N | AG8: N | AH8: Y | AI8: N | AJ8: Y | AK8: https://github.com/mariusbock/dl-for-har/tree/main | AL8: Y * (there are model weights. Correspondance with the author revealed they do not know what trainings they are the result of.) | AM8: Y | AP8: Y | AS8: =IF(AND(AP8="N", ISBLANK(AQ8)), "THIS", "")
H9: RealWorld HAR | I9: Y | K9: 50 | L9: N/A | M9: N/A | N9: 15 | O9: N/A | P9: N/A | Q9: N/A | R9: 8 | S9: Walking upstairs, walking downstairs, jumping, lying, standing, sitting, running, walking, (null) | T9: N/A | U9: N/A | AS9: =IF(AND(AP9="N", ISBLANK(AQ9)), "THIS", "")
B10: 151 | C10: Handling heterogeneity in Human Activity Recognition data by a compact Long Short Term Memory based deep learning approach | D10: Ahmed Cemiloglu | E10: https://doi.org/10.1016/j.engappai.2025.110788 | F10: Aug | G10: 2025 | H10: HHAR | I10: Y | K10: 100, 200 | L10: N/A | M10: Samsung Galaxy Gear and LG G | N10: 9 | O10: 25-30 yo | P10: Semi- or highly-supervised | Q10: Y (5 min/activity) | R10: 6 | S10: stand, sit, walk, stairsup, stairsdown, bike | T10: N/A | U10: B | V10: LSTM-CNN | W10: Y | X10: TensorFlow/Keras | Y10: N | AA10: 60 | AB10: N/A | AC10: SS. 70/15/15 | AD10: F1, Precision, Recall, Accuracy | AE10: Fig. 4, Table 5 | AF10: Y (Table 5) | AG10: Y | AH10: N | AI10: N | AJ10: N | AL10: N | AM10: N | AN10: IS | AP10: N | AQ10: ANR | AS10: =IF(AND(AP10="N", ISBLANK(AQ10)), "THIS", "")
B11: 59 | C11: Activity classification using a single wrist-worn accelerometer | D11: Saisakul Chernbumroong | E11: https://doi.org/10.1109/SKIMA.2011.6089975 | F11: Sep | G11: 2011 | H11: SC | I11: N/A | K11: 33 | L11: 2 | M11: eZ430-Chronos | N11: 7 | O11: 2 F, 27-35 yo | P11: Semi- or highly-supervised | Q11: N | R11: 5 | S11: Sitting, Standing, Lying, Walking, Running | T11: See Table 2 | U11: ND | V11: DT (C4.5) and ANN | W11: Y | X11: WEKA (DT) | Y11: Y | Z11: See Table 1 | AA11: 3.88 | AB11: 50 | AC11: 5-fold CV (10 runs) | AD11: Accuracy, F1 | AE11: Table IV | AF11: N | AG11: N | AH11: N | AI11: N | AJ11: N | AL11: N | AM11: N | AN11: IP | AO11: NOTE: DT is likely replicable. | AP11: N | AQ11: DNA | AS11: =IF(AND(AP11="N", ISBLANK(AQ11)), "THIS", "")
B12: 39 | C12: Temporal Alignment Improves Feature Quality: An Experiment on Activity Recognition with Accelerometer Data | D12: Hongjun Choi | E12: https://doi.org/10.1109/CVPRW.2018.00075 | F12: Jun | G12: 2018 | H12: SC | I12: N/A | K12: N/A | L12: N/A | M12: GENEActiv sensor | N12: 50 | O12: 18-64 yo | P12: Semi- or highly-supervised | Q12: Y | R12: 7 | S12: Walking (treadmill at 1mph), Walking (treadmill at 4mph), Running (treadmill at 6mph, 5% grade), Seated/folding/stacking laundry, Standing/fidgeting with hand while talking, Hard surface walking holding filled coffee cup, Walking down stairs (5 floors) | T12: N/A | U12: ND | V12: SVM (with RBF kernel) | W12: N | X12: Libsvm toolbox | Y12: 37 | Z12: "Finally, a 37-dimensional feature vector is used and calculated for each window for SVM training and prediction. The final features include: 1) Mean, variance, and root mean square values of the acceleration values on each of Cx, Cy, Cz and CE respectively. 2) Pearson correlation coefficients between all combinations of Cx, Cy, Cz and CE, frequency domain entropy, and the PSD from FFT values. 3) Difference between maximum and minimum accelerations on each axis (dx, dy, dz, dE), and the following 5 features [11]:" | AA12: Varies: 50 samples - 1000 samples | AB12: N/A | AC12: LOSO CV | AD12: Accuracy | AE12: Table 2 | AF12: Y | AG12: N | AH12: N | AI12: N | AJ12: N | AL12: N | AM12: N | AN12: IS | AP12: N | AQ12: DNA | AS12: =IF(AND(AP12="N", ISBLANK(AQ12)), "THIS", "")
B13: 132 | C13: Ensemble Methods for Classification of Physical Activities from Wrist Accelerometry | D13: Aok Kumar Chowdhury | E13: 10.1249/MSS.0000000000001291 | F13: Sept | G13: 2017 | H13: PAMAP2 | I13: Y | K13: 100 | L13: 16 | M13: Colobri IMU | N13: 9 | O13: See Table 1 | P13: Semi- or highly-supervised | Q13: N | R13: 8 (from 12) | S13: lying down, sitting, standing, walking running, cycling, ascending stairs, descending stairs | T13: N/A | U13: D | V13: ensemble method. BDT, KNN, SVM, ANN, WMV, NB cominer, and BKS combiner | W13: Y | X13: Matlab | Y13: Y | Z13: See Sec. Feature Extraction | AA13: 10 | AB13: 50 | AC13: LOSO CV | AD13: F1 | AE13: Tables 2-4 | AF13: Y | AG13: Y | AH13: Y | AI13: N | AJ13: Y | AK13: https://github.com/alokchy04/Decision-Fused-Ensembles-for-PA-Classification-from-Wrist-Worn-Accelerometer | AL13: N | AM13: Y | AP13: Y | AR13: ANN is missing seed, so you may get slightly different results. Also, data is in already generated features. | AS13: =IF(AND(AP13="N", ISBLANK(AQ13)), "THIS", "")
H14: SC | I14: Y* (extracted features) | J14: https://github.com/alokchy04/Decision-Fused-Ensembles-for-PA-Classification-from-Wrist-Worn-Accelerometer/tree/master/FET | K14: 32 | L14: 2 | M14: Empatica E4 | N14: 8 | O14: See Table 1 | P14: Semi- or highly-supervised | Q14: N | R14: 5 | S14: sit or stand still, self-paced comfortable walk, self-paced brisk walk, jogging, and fast-run | T14: N/A | U14: ND | AS14: =IF(AND(AP14="N", ISBLANK(AQ14)), "THIS", "")
H15: SC | I15: Y* (extracted features) | K15: 20 | L15: 6 | M15: ActiGraph GT3X+ | N15: 17 | O15: See Table 1 | P15: Semi- or highly-supervised | Q15: N | R15: 7 | S15: Lying down, sitting (handwriting, computer game), standing with upper body movements (throw and catch, laundry task, floor sweeping), walking (comfortable overground walk, brisk overground walk, brisk treadmill walk), running, basketball, and dance | T15: N/A | U15: ND | AS15: =IF(AND(AP15="N", ISBLANK(AQ15)), "THIS", "")
B16: 155 | C16: Situation identification in smart wearable computing systems based on machine learning and Context Space Theory | D16: Giuseppe D'Aniello | E16: https://doi.org/10.1016/j.inffus.2023.102197 | F16: April | G16: 2024 | H16: Extrasensory | I16: Y | K16: 25 | L16: N/A | M16: N/A | N16: 60 | O16: N/A | P16: Free-living | Q16: N/A | R16: 5 | S16: Sitting, standing, lying down, walking, running | T16: Table 2 | U16: N/A | V16: ANN, NB, KNN, RF, and DT | W16: Y | X16: Python and sci-kit learn | Y16: Y (from the original authors of the dataset) | Z16: "magnitude standard deviation (std), magnitude moment 4, magnitude 75-percentile, magnitude log energy band 2, magnitude log energy band 3, magnitude log energy band 4, mean-x, mean-y, mean-z, std-x, std-y, std-z, direction cosine similarity" | AA16: 20 | AB16: 0 | AC16: 5-fold CV | AD16: Accuracy, F1, Precision, Recall | AE16: Table 5 | AF16: N (they include classwise evaluations just not of wrist only) | AG16: Y | AH16: N | AI16: N | AJ16: Y | AK16: https://github.com/knowmis/SAWCS-Situation-Identification-in-Smart-Wearable-Computing-Systems | AL16: N | AM16: Y | AP16: Y | AS16: =IF(AND(AP16="N", ISBLANK(AQ16)), "THIS", "")
B17: 83 | C17: Comparing Supervised Learning Techniques on the Task of Physical Activity Recognition | D17: Anthony Dalton | E17: https://doi.org/10.1109/TITB.2012.2223823 | F17: Jan | G17: 2013 | H17: SC | I17: N/A | K17: 132 | L17: 6 | M17: N/A | N17: 25 | O17: 10 M, 15 F, mean age: 23.6 (2.41) yo | P17: Free-living | Q17: N | R17: 19 | S17: See Table 1 | T17: See Table 1 | U17: D | V17: C4.5, NB, BayesNet, IB1, IBK, KStar, JRip, SVM, MLP, AdaBoost, AdaBoostM1, Bagging,MultiBoost, Vote (Table IV) | W17: Y | X17: MATLAB and WEKA | Y17: Y | Z17: See Table II | AA17: 1 | AB17: 50 | AC17: LOSO CV | AD17: Kappa | AE17: Table 5 | AF17: N | AG17: Y | AH17: N | AI17: N | AJ17: N | AL17: N | AM17: Y | AP17: N | AQ17: DNA | AS17: =IF(AND(AP17="N", ISBLANK(AQ17)), "THIS", "")
B18: 99 | C18: Recognition of Human Behavior for Assisted Living Using Dictionary Learning Approach | D18: Pubali De | E18: https://doi.org/10.1109/JSEN.2017.2787616 | F18: Dec | G18: 2017 | H18: WHARF | I18: Y | K18: 32 | L18: 3 | M18: N/A | N18: 16 | O18: 11 M, 5 W | P18: N/A | Q18: N/A | R18: 7 | S18: getting up from the bed (GUB), sitting down on a chair (SDC) and standing up from a chair (SUC), reiterated actions (climbing stairs (CS) and walking (WK)) and complex actions (drinking water (DW) and pouring water from glasses (PWG)) | T18: N/A | U18: N/A | V18: K-singular value decomposition (K-SVD) (theirs), SVM, KNN, SRC, CRC-RLS, competing [12] | W18: Y | X18: N/A | Y18: N/A | AA18: N/A | AB18: N/A | AC18: SS. 80/20 | AD18: Accuracy, TN, TP | AE18: Table 1, 3 | AF18: Y | AG18: N | AH18: N | AI18: N | AJ18: N | AL18: N | AM18: N | AN18: IS | AP18: N | AQ18: TTS | AS18: =IF(AND(AP18="N", ISBLANK(AQ18)), "THIS", "")
B19: 46 | C19: Multi-Criteria Analysis of Sensor Reliability for Wearable Human Activity Recognition | D19: Yilin Dong | E19: https://doi.org/10.1109/JSEN.2021.3089579 | F19: Jun | G19: 2021 | H19: MHEALTH | I19: Y | K19: 50 | L19: N/A | M19: N/A | N19: 10 | O19: Diverse profiles (see paper) | P19: Semi- or highly-supervised | Q19: Y | R19: 12 | S19: standing still, sitting and relaxing, lying down, walking, climbing stairs, waist bends forward, frontal elevation of arms, knees bending, cycling, jogging, running, jump front and back | T19: N/A | U19: R | V19: SVM, Hidden conditional random forest (HCRF), and CNN. They propose a fused LSTM (which is not relevant for this review) | W19: Y | X19: MATLAB | Y19: Y for tranditional models | Z19: "hand-crafted features" | AA19: N/A | AB19: N/A | AC19: 10-fold CV (80/20 split within folds) | AD19: Accuracy | AE19: Fig. 7 | AF19: Y | AG19: Y | AH19: N | AI19: N | AJ19: N | AL19: N | AM19: N | AN19: IS | AP19: N | AQ19: TTS | AS19: =IF(AND(AP19="N", ISBLANK(AQ19)), "THIS", "")
B20: 87 | C20: Temporal-channel convolution with self-attention network for human activity recognition using wearable sensors | D20: Ehab Essa | E20: https://doi.org/10.1016/j.knosys.2023.110867 | F20: Oct | G20: 2023 | H20: WHARF | I20: Y | K20: 32 | L20: N/A | M20: N/A | N20: 16 | O20: N/A | P20: Semi- or highly-supervised | Q20: N/A | R20: 14 | S20: Not fully specified, but included activities "such as brushing teeth, sitting down on a chair, eating with a spoon, climbing the stairs, and walking" | T20: N/A | U20: R | V20: LSTM, transformer, CSNET, TCCSNET | W20: Y | X20: TensorFlow/Keras | Y20: N | AA20: N/A | AB20: N/A | AC20: LOSO CV | AD20: Accuracy, F1, Precision, Recall | AE20: Table 5 | AF20: Y | AG20: N | AH20: Y | AI20: N | AJ20: N | AL20: N | AM20: N | AN20: IS | AP20: N | AQ20: ANR | AS20: =IF(AND(AP20="N", ISBLANK(AQ20)), "THIS", "")
B21: 13 | C21: Matched Filter Interpretation of CNN Classifiers with Application to HAR | D21: Mohammed M. Farag | E21: https://doi.org/10.3390/s22208060 | F21: Oct | G21: 2022 | H21: WISDM | I21: Y | K21: 20 | L21: N/A | M21: N/A | N21: 29 | O21: N/A | P21: N/A | Q21: N | R21: 6 | S21: Walking, Upstairs, Downstairs, Sitting, Lying, Jogging | T21: N/A | U21: N/A | V21: MF CNN | W21: N | X21: Keras/Tensorflow | Y21: N | AA21: 2.6 | AB21: 25 | AC21: SS. 64/16/24 | AD21: Accuracy, F1 | AE21: Table 3 | AF21: Y | AG21: Y | AH21: Y | AI21: N | AJ21: N | AL21: N | AM21: Y | AP21: N | AQ21: TTS | AS21: =IF(AND(AP21="N", ISBLANK(AQ21)), "THIS", "")
B22: 14 | C22: AccNet24: A deep learning framework for classifying 24-hour activity behaviours from wrist-worn accelerometer data under free-living environments | D22: Vahid Farrahi | E22: https://doi.org/10.1016/j.ijmedinf.2023.105004 | F22: Apr | G22: 2023 | H22: CAPTURE-24 | I22: Y | K22: 100 | L22: N/A | M22: Axivity AX3 | N22: 151 | O22: 18-91 yo | P22: Free-living | Q22: N | R22: 4 | S22: Sleep, sed, lpa, mvpa | T22: Table 1 | U22: N/A | V22: Balanced RF, ANN, SVM, DT, NB, Acc-Net | W22: Y | X22: MATLAB, pyts package | Y22: Y (when applicable) | Z22: "For each window, we extracted a 112-dimensional feature vector. These features were selected from an extensive list of time and frequency domain features described in previous studies [18,24,25] and are listed in online supplemental Table 1. The extracted features were used as inputs for balanced RF, ANN, SVM, DT, and NB to classify sleep, sedentary behaviour, LPA, and MVPA. " | AA22: 30 | AB22: 0 | AC22: SS. 67/16.5/16.5 | AD22: Accuracy | AE22: Fig. 3 | AF22: Y | AG22: N | AH22: N | AI22: N | AJ22: N | AL22: N | AM22: N | AN22: IP | AP22: N | AQ22: TTS | AS22: =IF(AND(AP22="N", ISBLANK(AQ22)), "THIS", "")
B23: 85 | C23: A Comparative Study on Fitness Activity Recognition | D23: Igor Lopes de Faria | E23: https://doi.org/10.1145/3243082.3267452 | F23: Oct | G23: 2018 | H23: SC | I23: N/A | K23: N/A | L23: N/A | M23: N/A | N23: 4 | O23: 2 M, 2 F, 25-30 yo | P23: Semi- or highly-supervised | Q23: Y | R23: 3 | S23: walking and running on the tread- mill and the dumbbell biceps curl | T23: "The treadmill speed could not be more than seven kilometers per hour and the running speed could not be less than this value. For the exercise of stimulating biceps it was not necessary to use dumbbells, only the execution of the movement, being a choice of the volunteer to use the dumbbells or not." | U23: N/A | V23: KNN, j48, NB, SVM, MLP | W23: Y | X23: R | Y23: Y | Z23: "In the pre-processing phase, we extracted two time-domain features for these sensors: average and standard deviation." | AA23: 2 | AB23: 0 | AC23: 10-fold CV | AD23: Accuracy | AE23: Table 1 | AF23: N | AG23: N | AH23: N | AI23: N | AJ23: N | AL23: N | AM23: N | AN23: IP | AP23: N | AQ23: DNA | AS23: =IF(AND(AP23="N", ISBLANK(AQ23)), "THIS", "")
B24: 7 | C24: Improving Activity Recognition while Reducing Misclassification of Unknown Activities | D24: Andrea Fasciglione | E24: https://doi.org/10.1109/WETICE53228.2021.00039 | F24: Oct | G24: 2021 | H24: SC | I24: N/A | K24: 256 | L24: N/A | M24: N/A | N24: 8 | O24: "Healthy" | P24: N/A | Q24: N/A | R24: 17 | S24: 1. Relaxing on a chair , 7. Brushing Teeth, 13. Downstairs, 2. Keyboard Typing, 8. Sweeping, 14. Walking, 3. Using the Laptop, 9. Vacuuming, 15. Walking Fast, 4. Handwriting, 10. Eating (a soup), 16. Upstairs Fast, 5. Washing Hands, 11. Dusting surface, 17. Upstairs, 6. Washing Face, 12. Rubbing surface | T24: N/A | U24: D | V24: Ensemble method. Five traditional models predicting at once (SVM, DT, RF, KNN, and gaussian NB). Majority of the votes is the final prediction; no majority vote "other" class. | W24: N | X24: N/A | Y24: Y | Z24: "During the features extraction, the sliding window passes over the data and, for each axis (X, Y, Z), different measures are extracted from the data contained in the window: mean, variance, standard deviation, median absolute deviation, percentiles (10Th, 25Th, 75Th, 90Th), obtaining a total of 24 features." | AA24: N/A (Features are extracted from 2s windows with 95% overlap but results are discussed from 5s windows (50 samples). They also investigated multiple window sizes to remove outliers. | AB24: N/A | AC24: SS. 75/25 | AD24: F1 | AE24: Table 2 and 3 | AF24: N | AG24: Y | AH24: N | AI24: N | AJ24: N | AL24: N | AM24: N | AN24: IS | AP24: N | AQ24: DNA | AS24: =IF(AND(AP24="N", ISBLANK(AQ24)), "THIS", "")
B25: 152 | C25: Modelling time-series data generation with diffusion models for triaxial data | D25: Francisco M. Garcia-Moreno | E25: https://doi.org/10.1016/j.asoc.2025.114195 | F25: Jan | G25: 2026 | H25: WISDM | I25: Y | K25: 20 | L25: N/A | M25: N/A | N25: 51 | O25: N/A | P25: Semi- or highly-supervised | Q25: Y (See Table 2) | R25: 5 (a subset of the original 18) | S25: walking, jogging, stairs (ascending + descensing), sitting, and standing | T25: N/A | U25: N/A | V25: Diffusion Models using recurrence plots: VGG-16, ResNet-18, ResNet-34, ResNext-50, InceptionResNetv2 | W25: Y | X25: N/A | Y25: N | AA25: 2.56 (129 samples) | AB25: 0 | AC25: LOTO (leave one trial out) CV and LOSO CV | AD25: Accuracy, F1, Precision, Recall, and Specificity | AE25: Tables 4-11 and Fig. 8+ 9 | AF25: N | AG25: N | AH25: N | AI25: N | AJ25: Y | AK25: https://github.com/crowsonkb/k-diffusion | AL25: N | AM25: Y | AP25: Y | AS25: =IF(AND(AP25="N", ISBLANK(AQ25)), "THIS", "")
B26: 15 | C26: How Accurately Can Your Wrist Device Recognize Daily Activities and Detect Falls? | D26: Martin Gjoreski | E26: https://doi.org/10.3390/s16060800 | F26: May | G26: 2016 | H26: SC (Faculty of Sports) | I26: Y* | J26: Link seems dead. | K26: 40 | L26: 4 | M26: Shimmer 2R | N26: 10 | O26: Avg ave 27.2 (3.1) yo, 8 M, 2 F | P26: Semi- or highly-supervised | Q26: N | R26: 10 | S26: lying (23%), standing (17%), walking (14%), sitting (12%), cycling (10), on all fours (8%), kneeling (6%), running (5%), bending and transition | T26: N/A | U26: R | V26: J48, RF, NB, SVM, KNN | W26: Y | X26: N/A | Y26: Y | Z26: See Table 2 | AA26: 4 | AB26: 50 | AC26: LOSO CV | AD26: Accuracy | AE26: Fig. 7 | AF26: N | AG26: Y | AH26: Y | AI26: N | AJ26: N | AL26: N | AM26: N | AN26: IP | AP26: N | AQ26: ANR | AS26: =IF(AND(AP26="N", ISBLANK(AQ26)), "THIS", "")
H27: SC (JSI) | I27: Y* | J27: Link seems dead. | K27: 50 | L27: 4 | M27: Xsens-MTx inertial sensors | N27: 5 | O27: Healthy, 29.4 (2.1) yo, 4 M, 1 F | P27: Semi- or highly-supervised | Q27: N | R27: 10 | S27: cycling (18%), walking (17%), standing (14%), lying (13%), sitting (11%), running (9%), on all fours (7%), kneeling (5), bending (3.5), and transition (2.5%) | T27: N/A | U27: B | AE27: Fig. 6 | AF27: N | AG27: Y | AH27: Y | AI27: N | AS27: =IF(AND(AP27="N", ISBLANK(AQ27)), "THIS", "")
H28: Opportunity | I28: Y | K28: 30 | L28: N/A | M28: InertiaCube3 | N28: 3 | O28: N/A | P28: Semi- or highly-supervised | Q28: N | R28: 4 | S28: standing (50%), walking (28%), sitting (19%), and lying (3%) | T28: N/A | U28: B | AE28: Fig. 8 | AF28: Y | AG28: N | AH28: Y | AI28: N | AS28: =IF(AND(AP28="N", ISBLANK(AQ28)), "THIS", "")
B29: 31 | C29: Reducing the Impact of Sensor Orientation Variability in Human Activity Recognition Using a Consistent Reference System | D29: Manuel Gil-Martín | E29: https://doi.org/10.3390/s23135845 | F29: Jun | G29: 2023 | H29: PAMAP2 | I29: Y | K29: 100 | L29: N/A | M29: N/A | N29: 9 | O29: N/A | P29: Semi- or highly-supervised | Q29: N | R29: 12 | S29: lying, sitting, standing, walking, running, cycling, Nordic walk, ascending stairs, descending stairs, ironing, vacuum cleaning, and rope jumping | T29: N/A | U29: D | V29: CNN | W29: N | X29: N/A | Y29: N | AA29: 5 | AB29: 20 | AC29: LOSO CV and 10-fold CV by subject | AD29: Accuracy | AE29: Table 3 and 4 | AF29: N | AG29: Y | AH29: Y | AI29: N | AJ29: N | AL29: N | AM29: Y | AP29: N | AQ29: TTS | AR29: NOTE: LOSO may be reproducible. | AS29: =IF(AND(AP29="N", ISBLANK(AQ29)), "THIS", "")
B30: 88 | C30: Towards Learning Discrete Representations via Self-Supervision for Wearables-Based Human Activity Recognition | D30: Harish Haresamudram | E30: https://doi.org/10.3390/s24041238 | F30: Feb | G30: 2024 | H30: HHAR | I30: Y | K30: 50 (downsampled) | L30: N/A | M30: Smartwatches (LG G and Samsung Galaxy Gear) | N30: 9 | O30: N/A | P30: Semi- or highly-supervised | Q30: Y | R30: 6 | S30: Biking, sitting, going up and down the stairs, standing, and walking | T30: N/A | U30: N/A | V30: CNN, ConvLSTM, GRU, Multi-task self supervised, autoencoder, simclr, cpc, enchanced cpc, vq cpc + lstm, vq + gru | W30: Y | X30: PyTorch | Y30: N | AA30: 2 | AB30: 0 (train), 50 (overlap for target) | AC30: 5-fold CV | AD30: F1 | AE30: Table 2, Table 8. Table 6 uses embeddings learned from CAPTURE-24 data. | AF30: N | AG30: N | AH30: Y | AI30: N | AJ30: N | AL30: N | AM30: Y | AP30: Y | AS30: =IF(AND(AP30="N", ISBLANK(AQ30)), "THIS", "")
B31: 76 | C31: Deep Learning Approach for Complex Activity Recognition using Heterogeneous Sensors from Wearable Device | D31: Narit Hnoohom | E31: https://doi.org/10.1109/RI2C51727.2021.9559773 | F31: Sep | G31: 2021 | H31: WISDM | I31: Y | K31: 20 | L31: N/A | M31: Android Wear 1.5 wearable (LG G Watch) | N31: 51 | O31: N/A | P31: N/A | Q31: Y | R31: 18 | S31: See Table 2 | T31: N/A | U31: N/A | V31: Att-BiLSTM and BiLSTM | W31: Y | X31: TensorFlow, Numpy, Pandas, and Scikit-Learn libraries | Y31: N | AA31: Multiple tested | AB31: Multiple tested | AC31: 10-fold CV | AD31: Accuracy, F1 | AE31: Table 4 | AF31: N | AG31: Y | AH31: N | AI31: N | AJ31: N | AL31: N | AM31: Y | AP31: N | AQ31: TTS | AS31: =IF(AND(AP31="N", ISBLANK(AQ31)), "THIS", "")
B32: 61 | C32: Activity Recognition with Wristband Based on Histogram and Bayesian Classifiers | D32: Yi-Cong Huang | E32: https://doi.org/10.1109/SIPROCESS.2019.8868412 | F32: Jul | G32: 2019 | H32: SC | I32: N/A | K32: N/A | L32: N/A | M32: N/A | N32: 8 | O32: N/A | P32: N/A | Q32: N/A | R32: 5 | S32: walking, office working, eating, sporting and resting | T32: N/A | U32: N/A | V32: Historgram with Bayesian classifier | W32: N | X32: N/A | Y32: Y | Z32: "Some useful motion features of these 4 seconds data blocks such as the energies, the time indices corresponding to the zero crossing points as well as the time indices of the crossing points of three different threshold values are extracted. Based on these motion feature vectors, a k means clustering algorithm [13] with the one norm operator as the criterion is performed for assigning the feature vectors [14]. Here, the feature vectors are classified into 9 clusters. Since the features are related to the energies and the time indices of the crossing points of different threshold values, the obtained cluster labels are related to the magnitudes of the motions." See Figure 3.4 | AA32: 20 s increment taken from 1 m, split into 4s windows for feautre extraction | AB32: 50 | AC32: N/A | AD32: Accuracy | AE32: Table 1, 2, 3 | AF32: Y | AG32: N | AH32: N | AI32: N | AJ32: N | AL32: N | AM32: N | AN32: IF | AP32: N | AQ32: DNA | AS32: =IF(AND(AP32="N", ISBLANK(AQ32)), "THIS", "")
B33: 37 | C33: A Comprehensive Analysis on Wearable Acceleration Sensors in Human Activity Recognition | D33: Majid Janidarmian | E33: https://doi.org/10.3390/s17030529 | F33: Feb | G33: 2017 | H33: Aggregated 14 datasets | I33: Y | K33: N/A | L33: N/A | M33: Listed for each dataset | N33: 228 across all datasets (not all have wrist data) | O33: 19-83 yo | P33: Variable across datasets | Q33: N | R33: 9 | S33: walking, running, jogging, cycling, standing, sitting, lying down, ascending and descending stairs | T33: N/A | U33: B | V33: 293 different classifiers (DT, discriminant analysis, SVM, KNN, ensemble methods, NB, and NN) | W33: Y | X33: N/A | Y33: Y | Z33: See Table 1 | AA33: Varies from 1 - 15 s in 1s intervals | AB33: 0 | AC33: LOSO CV | AD33: Accuracy | AE33: Fig. 5 | AF33: N | AG33: Y | AH33: N | AI33: N | AJ33: N | AL33: N | AM33: Y | AP33: Y | AS33: =IF(AND(AP33="N", ISBLANK(AQ33)), "THIS", "")
B34: 79 | C34: Topological persistence guided knowledge distillation for wearable sensor data | D34: Eun Som Jeon | E34: https://doi.org/10.1016/j.engappai.2023.107719 | F34: Apr | G34: 2024 | H34: GENEActiv | I34: Y | K34: 100 | L34: N/A | M34: GENEActiv | N34: N/A | O34: N/A | P34: Semi- or highly-supervised | Q34: N | R34: 14 | S34: See Figure 5 | T34: N/A | U34: N/A | V34: Teacher (CNN) / Student (WRN, wideresnet) model | W34: N | X34: Scikit-TDA (images) | Y34: N/A | AA34: 5 | AB34: 0 | AC34: SS. 70/30 | AD34: Accuracy | AE34: Table 2 and 3 | AF34: Y | AG34: N | AH34: Y | AI34: N | AJ34: N* (they say released upon acceptance) | AL34: N | AM34: N | AN34: IP | AP34: N | AQ34: TTS | AS34: =IF(AND(AP34="N", ISBLANK(AQ34)), "THIS", "")
B35: 105 | C35: Deep Neural Networks for Time Series Classification in Human Activity Recognition | D35: Shreehar Joshi | E35: https://doi.org/10.1109/IEMCON53756.2021.9623228 | F35: Oct | G35: 2021 | H35: WISDM | I35: Y | K35: 20 | L35: N/A | M35: N/A | N35: 51 | O35: N/A | P35: N/A | Q35: Y | R35: 13 (from 18) | S35: 1. Non-hand-oriented activities: a. Standing, b. Jogging, c. Stairs, d. Sitting, e. Walking 2. Hand-oriented activities: a. Typing, b. Writing, c. Brushing, d. Folding Clothes, e. Dribbling (Basketball), f. Playing (Catch), g. Eating (Pasta), h. Clapping "While the dataset initially consisted of raw data for 18 activities, those that were highly similar in nature (for instance, different variants of eating such as eating chips, sandwich, pasta, etc) are discarded and only 13 of them that are unique are used for this research." | T35: N/A | U35: N/A | V35: BiLSTM, CNN-LSTM, ConvLSTM, and CNN | W35: Y | X35: keras and sklearn | Y35: N | AA35: 4 | AB35: 50 | AC35: SS. 80/20 | AD35: Accuracy | AE35: Table 1, Fig. 5 | AF35: Y | AG35: Y | AH35: N | AI35: N | AJ35: N | AL35: N | AM35: Y | AP35: N | AQ35: TTS | AS35: =IF(AND(AP35="N", ISBLANK(AQ35)), "THIS", "")
B36: 43 | C36: Rich learning representations for human activity recognition: How to empower deep feature learning for biological time series | D36: Ria Kanjilal | E36: https://doi.org/10.1016/j.jbi.2022.104180 | F36: Oct | G36: 2022 | H36: Mannini | I36: Y | K36: 90 | L36: N/A | M36: Wocket | N36: 53 | O36: 33 "adults", 20 "youth" | P36: Semi- or highly-supervised | Q36: N | R36: 4 | S36: ambulation, cycling, other, sedentary | T36: N/A | U36: N/A | V36: 6 popular SotA models. Deep feed-forward neural network (DFNN), autoencoder deep feedforward neural network (AE-DFNN), one-dimensional convolutional neural network (1D-CNN), two-dimensional convolutional neural network (2D-CNN), recurrent neural network with long short-term memory (RNN-LSTM) and feature engineering using deep feed-forward neural network (FE-DFNN). Their novel model is a 2D CNN using a spectrogram as input. | W36: Y | X36: N/A | Y36: N | AA36: 30 | AB36: N/A | AC36: LOSO CV | AD36: Accuracy | AE36: Table 4 | AF36: N | AG36: Y | AH36: N | AI36: N | AJ36: N | AL36: N | AM36: N | AN36: IS | AP36: N | AQ36: ANR | AS36: =IF(AND(AP36="N", ISBLANK(AQ36)), "THIS", "")
B37: 58 | C37: A general framework for sensor-based human activity recognition | D37: Lukas Köping | E37: https://doi.org/10.1016/j.compbiomed.2017.12.025 | F37: Apr | G37: 2018 | H37: SC | I37: N/A | K37: 67 | L37: N/A | M37: Microdoft Band 2 | N37: 1 | O37: N/A | P37: Semi- or highly-supervised | Q37: N | R37: 11 | S37: 1. lying, 2. sitting, 3. standing, 4. walking, 5. bending, 6. getting up, 7. lying down, 8. putting a hand back, 9. sitting down, 10. standing up, and 11. stretching a hand. | T37: N/A | U37: N/A | V37: SVM (RBF kernel) | W37: N | X37: N/A | Y37: Y | Z37: N/A | AA37: 0.95 | AB37: 90 | AC37: N/A | AD37: Mean Average Precision (MAP) | AE37: Fig. 10, 11 | AF37: Y | AG37: Y | AH37: N | AI37: N | AJ37: Y* (only feature extraction, not full algorithm) | AK37: http://www.pr.iN/Aormatik.uni-siegen.de/en/ human-activity-recognition | AL37: N | AM37: Y | AP37: N | AQ37: DNA | AS37: =IF(AND(AP37="N", ISBLANK(AQ37)), "THIS", "")
B38: 62 | C38: A Deep Learning-Based Semantic Segmentation Model Using MCNN and Attention Layer for Human Activity Recognition | D38: Sang-hyub Lee | E38: https://doi.org/10.3390/s23042278 | F38: Feb | G38: 2023 | H38: SC | I38: N/A | K38: 15 | L38: N/A | M38: LIS2DS12TR, STMicroelectronics | N38: 8 | O38: All males, 20-40 yo | P38: Semi- or highly-supervised | Q38: Y | R38: 18 | S38: get-up, laying stand-up, picking, sitting, walking, walking-picking, walking-sitting, stand-up-walking, sitting-laying, get-up-stand-up, picking-walking,get-up-laying, laying-get-up, stand-up,=picking, stand-up-sitting, picking-sitting, sitting-stand-up | T38: N/A | U38: R | V38: Combinataions of GRU, RNN, LSTM, CNN, proposed model is MCNN with attention (16 evaluated in total) | W38: Y | X38: PyTorch | Y38: N | AA38: .6, 1.3, and 2.6 s (10, 20, and 40 samples) | AB38: 50 | AC38: LOSO CV | AD38: F1, Precision, Recall | AE38: Table 4 | AF38: Y | AG38: N | AH38: N | AI38: N | AJ38: N | AL38: N | AM38: Y | AP38: N | AQ38: DNA | AS38: =IF(AND(AP38="N", ISBLANK(AQ38)), "THIS", "")
B39: 115 | C39: Accelerometer Dense Trajectories for Activity Recognition and People Identification | D39: Roberto Leyva | E39: https://doi.org/10.1109/IWBF.2019.8739218 | F39: May | G39: 2019 | H39: SPHERE | I39: Y | K39: N/A | L39: N/A | M39: N/A | N39: N/A | O39: N/A | P39: N/A | Q39: N/A | R39: 10 (from 20) | S39: t_turn, t_straighten, t_stand_sit, t_stand_kneel, t_sit_stand, t_sit_lie, t_lie_sit, t_kneel_stand, t_bend, p_stand, p_squat, p_sit, p_lie, p_kneel, p_bent, a_walk, a_loadwalk, a_jump, a_descend, a_ascend | T39: N/A | U39: N/A | V39: DNN | W39: N | X39: MATLAB | Y39: Y | Z39: See Sec. III A and B | AA39: N/A | AB39: N/A | AC39: LOSO CV | AD39: Mean Average Precision (MAP) | AE39: Table 1 | AF39: N | AG39: N | AH39: Y | AI39: N | AJ39: N | AL39: N | AM39: N | AN39: IS | AP39: N | AQ39: ANR | AS39: =IF(AND(AP39="N", ISBLANK(AQ39)), "THIS", "")
B40: 112 | C40: Human activity recognition based on triaxial accelerometer using multi-feature weighted ensemble | D40: QingNan Li | E40: https://doi.org/10.1109/INDIN45582.2020.9442172 | F40: July | G40: 2020 | H40: SC | I40: N/A | K40: 200 | L40: N/A | M40: N/A | N40: 4 | O40: 2 F, 2 M | P40: N/A | Q40: N | R40: 8 | S40: shaking hands, waving hand, lying, walking, picking things up, bending over to pick things up, sit-down-stand-up, and open-close door | T40: N/A | U40: N/A | V40: KNN, attention LSTM, 1D CNN, ensemble method (theirs), CNN-LSTM | W40: Y | X40: N/A | Y40: Y | Z40: See Section IIC | AA40: 2 | AB40: 50 | AC40: SS. 60/12/28 | AD40: Accuracy | AE40: Fig. 4, Table 3 | AF40: Y | AG40: N | AH40: N | AI40: N | AJ40: N | AL40: N | AM40: N | AN40: IP | AP40: N | AQ40: DNA | AS40: =IF(AND(AP40="N", ISBLANK(AQ40)), "THIS", "")
B41: 103 | C41: Human Activity Recognition in Free Living Using a Wearable Sensor: A Two-Stage Approach | D41: Tianhui Li | E41: https://doi.org/10.1109/iCAST57874.2023.10359305 | F41: Nov | G41: 2023 | H41: SC | I41: N/A | K41: 16 | L41: N/A | M41: N/A | N41: 1 | O41: "Healthy" male | P41: Free-living | Q41: N | R41: 5 | S41: desk working, driving, walking, downstairs, upstairs | T41: N/A | U41: ND | V41: DT and DL (with Covs). They use a two-stage classifier: DT for classification of exercise or not, DL for within the two classes. | W41: N | X41: Scikit learn | Y41: Y | Z41: "Then, statistical features were extracted from the segments including mean, maximum, minimax, standard derivation, kurtosis, and skewness. Substantially, the features were standardized by removing the mean and scaling to unit variance" | AA41: 2 | AB41: 50 | AC41: SS. 70/30 | AD41: Accuracy, Sensitivity, Specificity | AE41: Table 3 | AF41: N | AG41: N | AH41: Y | AI41: N | AJ41: N | AL41: N | AM41: N | AN41: IP | AP41: N | AQ41: DNA | AS41: =IF(AND(AP41="N", ISBLANK(AQ41)), "THIS", "")
B42: 142 | C42: Frequency-Aware Masked Autoencoders for Human Activity Recognition using Accelerometers | D42: Niels R. Lorenzen | E42: 10.1109/EMBC58623.2025.11252605 | F42: Jul | G42: 2025 | H42: UK BioBank | I42: Y | K42: 30 (downsampled from 100) | L42: N/A | M42: Axivity AX3 | N42: 103,618. Additionally, they used 151 participants data from CAPTURE-24 to fine-tune and evaluate the model. | O42: N/A | P42: Free-living | Q42: N | R42: 6 activities (unless otherwise specified. Models were fine-tuned on CAP-24 data.) | S42: Bicycling, walking, mixed, vehicle, sit-stand, and sleep | T42: N/A | U42: N/A | V42: TMAE (transformer masked autoencoder) | W42: N | X42: N/A | Y42: N | AA42: 10 | AB42: 0 | AC42: SS. 80 (80/20 as 5 fold CV) / 20 split | AD42: Macro F1, Cohen's Kappa | AE42: Table 1, Figure 2 | AF42: Y | AG42: N | AH42: N | AI42: N | AJ42: N | AL42: N | AM42: Y | AP42: N | AQ42: TTS | AS42: =IF(AND(AP42="N", ISBLANK(AQ42)), "THIS", "")
B43: 98 | C43: Research on human activity recognition based on active learning | D43: Rong Liu | E43: https://doi.org/10.1109/ICMLC.2010.5581050 | F43: Jul | G43: 2010 | H43: MIT (not cited) Bao + Intille | I43: Y | K43: N/A | L43: N/A | M43: N/A | N43: N/A | O43: N/A | P43: N/A | Q43: N/A | R43: 20 | S43: Includes walking, sitting, working on computer, standing, eating or drinking, running, bicycling, vacuuming, folding laundry. | T43: N/A | U43: D | V43: C4.5 DT | W43: N | X43: N/A | Y43: N/A | AA43: N/A | AB43: N/A | AC43: SS. Variable split, 25-45% in training set | AD43: Accuracy | AE43: Table 1, 2 | AF43: N | AG43: Y | AH43: N | AI43: N | AJ43: N | AL43: N | AM43: N | AN43: IF | AP43: N | AQ43: TTS | AS43: =IF(AND(AP43="N", ISBLANK(AQ43)), "THIS", "")
B44: 102 | C44: MFE-HAR: multiscale feature engineering for human activity recognitionusing wearable sensors | D44: Jianchao Lu | E44: https://doi.org/10.1145/3360774.3360787 | F44: Feb | G44: 2020 | H44: DaLiAc | I44: Y | K44: 204.8 | L44: N/A | M44: N/A | N44: 19 | O44: "healthy" | P44: Semi- or highly-supervised | Q44: N | R44: 13 | S44: sitting, lying, standing, washing dishes, vacuuming, sweeping, walking, ascending stairs, descending stairs, treadmill running, bicycling on ergometer (50W), bicycling on ergometer (100W) and rope jumping. | T44: N/A | U44: R | V44: GBDT, RF, LR, KNN, and SVM NOTE: their novel model uses more than wrist-accelerometer only data. | W44: Y | X44: Python 3.6 | Y44: Y | Z44: "3.1.1 Global Features. In this study, we extract six general features, i.e., mean, variance, maximum, minimum, skewness and kurtosis, as global features for each signal segment excluding non-stationary signals from every accelerometer axis. Besides the three-axis accelerometer signals, the magnitude of x, y and z axis is also used for feature extraction. In total, this results in 24 global features per sensor node by timing 4 (x,y,z and magnitude) and 6 (6 general features mentioned above). 3.1.2 Local Features. Similar to global features, mean, variance, maximum, minimum, skewness and kurtosis are extracted for each frame as local features. Thus, they comprise 24 (same as the number of global features)×4 (frames) = 96 local features. Moreover, 3 Delta local features, corresponding to the changes of signal pattern distribution are also calculated in this study." | AA44: 5 | AB44: 50 | AC44: N/A | AD44: Accuracy, F1, Precision, Recall | AE44: Fig. 4, 7 | AF44: Y | AG44: N | AH44: Y | AI44: N | AJ44: N | AL44: N | AM44: N | AN44: IP | AP44: N | AQ44: TTS | AS44: =IF(AND(AP44="N", ISBLANK(AQ44)), "THIS", "")
H45: MHEALTH | I45: Y | K45: 50 | L45: N/A | M45: N/A | N45: 10 | O45: N/A | P45: N/A | Q45: N | R45: 12 | S45: standing still, sitting and relaxing, lying down, walking, climbing stairs, waist bends forward, frontal elevation of arms, knees bending (crouching), cycling, jogging, running, and jump front and back. | T45: N/A | U45: R | AA45: 4 | AB45: 50 | AG45: Y | AH45: Y | AS45: =IF(AND(AP45="N", ISBLANK(AQ45)), "THIS", "")
B46: 51 | C46: Robust Single Accelerometer-Based Activity Recognition Using Modified Recurrence Plot | D46: Jianjie Lu | E46: https://doi.org/10.1109/JSEN.2019.2911204 | F46: Aug | G46: 2019 | H46: ASTRI | I46: Y | K46: 52 | L46: N/A | M46: ASTRI wrist band | N46: 11 | O46: "different genders and ages" | P46: N/A | Q46: N | R46: 5 | S46: walking, sitting, standing, squatting and lying | T46: N/A | U46: N/A | V46: 7 baselines: RF, SVM, CNN, DTW+1NN (dynamic time warping), STN+Clustering, LSTM+FCN, and RP+ResNET (their model is a novel RP+ResNet) | W46: Y | X46: N/A | Y46: Y | Z46: "a total of 21 statistical features in the time and frequency domains." | AA46: 5 | AB46: N/A | AC46: SS. In user-mixed experiments, 70/30. In user-independent experiments, data of 4 (for ASTRI Motion dataset) or 5 subjects (for ADL dataset) are selected randomly for testing. | AD46: Accuracy | AE46: Table 2 | AF46: Y | AG46: N | AH46: Y | AI46: N | AJ46: Y | AK46: https://github.com/lulujianjie/robust-single-accelerometer-based-activity-recognition-using-modified-recurrence-plot | AL46: Y | AM46: Y | AP46: Y | AS46: =IF(AND(AP46="N", ISBLANK(AQ46)), "THIS", "")
H47: WHARF | I47: Y | K47: 32 | L47: N/A | M47: N/A | N47: 16 | O47: N/A | P47: N/A | Q47: N/A | R47: 7 | S47: climbing stairs, drinking water, getting up bed, pouring water, sitting down, standing up, and walking | T47: N/A | U47: N/A | AS47: =IF(AND(AP47="N", ISBLANK(AQ47)), "THIS", "")
B48: 150 | C48: A two-stage multi-branch fusion model for human activity recognition based on sensor data transformed by gramian angular difference field | D48: Limeng Lu | E48: https://doi.org/10.1016/j.bspc.2025.109141 | F48: Mar | G48: 2026 | H48: SC (WSMC-HAR) | I48: Y | J48: Available upon request. | K48: 20 | L48: 2 | M48: N/A | N48: 7 | O48: All males. | P48: Semi- or highly-supervised | Q48: N/A | R48: 5 | S48: jogging, running, sitting, upstairs, downstairs | T48: N/A | U48: N/A | V48: Fusion model/GADF (theirs), CNN, LSTM-CNN, LSTM-RNN, GRF, GMN, Mdk-ResNet | W48: Y (They compare solely against other results from other papers. Results may not be directly compared.) | X48: Keras | Y48: N | AA48: 6.4 (128 samples) | AB48: 50 | AC48: N/A | AD48: Accuracy, Loss, F1,Precision, Recall | AE48: Table 4, Fig. 10 | AF48: Y (Fig 10) | AG48: N | AH48: Y | AI48: N | AJ48: N | AL48: N | AM48: Y | AP48: N | AQ48: TTS | AS48: =IF(AND(AP48="N", ISBLANK(AQ48)), "THIS", "")
B49: 97 | C49: Wearable Computing for Internet of Things: A Discriminant Approach for Human Activity Recognition | D49: Wei Lu | E49: https://doi.org/10.1109/JIOT.2018.2873594 | F49: Apr | G49: 2019 | H49: MHEALTH | I49: Y | K49: 50 | L49: N/A | M49: Shimmer2 | N49: 10 | O49: N/A | P49: Lab | Q49: Y | R49: 12 | S49: See Table 4 | T49: N/A | U49: R | V49: SVM, bagging, and KNN | W49: Y | X49: MATLAB | Y49: Y | AA49: 9 | AB49: 50 | AC49: SS. 80/20 | AD49: Accuracy, F1 Precision, Recall | AE49: Table 8, 9, 10, 11 | AF49: N | AG49: Y | AH49: Y | AI49: N | AJ49: N | AL49: N | AM49: N | AN49: IP | AP49: N | AQ49: TTS | AS49: =IF(AND(AP49="N", ISBLANK(AQ49)), "THIS", "")
B50: 130 | C50: Data augmentation for Human Activity Recognition with Generative Adversarial Networks | D50: Marcos Lupion | E50: 10.1109/JBHI.2024.3364910 | F50: April | G50: 2024 | H50: Cleland | I50: Y | K50: 51.2 | L50: 1.5 | M50: Shimmer 2R | N50: 395 | O50: "undergraduate students" | P50: Semi- or highly-supervised | Q50: N | R50: 18 | S50: hand washing, hair grooming, standing, sitting, walking, catching, passign, bouncing, seving floor, chopping vegs, arm curls, lateral arm raise, deadlifes, stepping, jogging, washing dishes, window washing, mizing food, ironing clothes, teeth brushing | T50: N/A | U50: D | V50: cGAN, cWGAN | W50: Y | X50: N/A | Y50: Y | Z50: Selected 18 final features from 24. They do not say which 18. | AA50: 4 | AB50: 0 | AC50: SS. 70/20/10 | AD50: F1 | AE50: Fig. 9 - 11 | AF50: N | AG50: N | AH50: N | AI50: N | AJ50: Y | AK50: https://github.com/marcoslupion/SyntheticAccelerometryHAR | AL50: N | AM50: Y | AP50: N | AQ50: TTS | AS50: =IF(AND(AP50="N", ISBLANK(AQ50)), "THIS", "")
B51: 41 | C51: Smart-Wearable Sensors and CNN-BiGRU Model: A Powerful Combination for Human Activity Recognition | D51: Hazma Ali Imran | E51: https://doi.org/10.1109/JSEN.2023.3338264 | F51: Dec | G51: 2023 | H51: WISDM | I51: Y | K51: N/A | L51: N/A | M51: N/A | N51: 51 | O51: 18-25 yo | P51: Semi- or highly-supervised | Q51: Y | R51: 18 | S51: See Figure 2 | T51: N/A | U51: D | V51: "HARDenseRNN" Deep RNN (with CNNs) | W51: Y | X51: TensorFlow | Y51: Y (when applicable) | Z51: Magnitude of signal | AA51: experimented with 64, 128, and 256 samples | AB51: 16, 32, 64 and 128-step overlap | AC51: 10-fold CV | AD51: Accuracy, F1, Precision, Recall, Sensitivity | AE51: Table 3 | AF51: Y | AG51: Y | AH51: Y | AI51: N | AJ51: N | AL51: N | AM51: Y | AP51: N | AQ51: TTS | AS51: =IF(AND(AP51="N", ISBLANK(AQ51)), "THIS", "")
B52: 63 | C52: Age Differences in Estimating Physical Activity by Wrist Accelerometry Using Machine Learning | D52: Mamoun T. Mardini | E52: https://doi.org/10.3390/s21103352 | F52: May | G52: 2021 | H52: SC (ChoresXL) | I52: N/A | K52: 100 | L52: N/A | M52: ActiGraph GT3X-BT | N52: 253 | O52: 20+ yo, able to read and write in English | P52: Semi- or highly-supervised | Q52: N/A | R52: 33 | S52: Leisure Walk, Rapid Walk, Light Gardening, Yard Work, Prepare Serve Meal, Digging, Straightening Up Dusting, Washing Dishes, Unloading Storing Dishes, Walk at RPE 1, Personal Care, Dressing, Walk at RPE 5, Sweeping, Vacuuming, Stiar Descent, Stair Ascent, Trash Remoal, Replacign Sheets on a Bed, Stretching Yoga, Mopping, Light Home Maintenance, Computer Work, Heavy Lifting, Shpping, Ironing, Laundry Washing, Stength Exercise Leg Curl, Strength Exercise Chest Press, Strength Exercise Leg Extension, TV Watching, Standing Still, Washing Windows. | T52: N/A | U52: R | V52: DT, RF, XGBoost, and LASSO. Classification tasks included PA type, sedentary vs not, locomotion vs not, and PA levels across 3 age groups (20-50, 50-70, 70+) | W52: Y | X52: N/A | Y52: Y | Z52: See Table 1 | AA52: 60 | AB52: 0 | AC52: 5-fold CV | AD52: Accuracy, AUC, Balanced Accuracy, F1 | AE52: Fig. 2 and 3 | AF52: Y | AG52: N | AH52: N | AI52: N | AJ52: N | AL52: N | AM52: N | AN52: IP | AP52: N | AQ52: DNA | AS52: =IF(AND(AP52="N", ISBLANK(AQ52)), "THIS", "")
B53: 78 | C53: User-Independent Recognition of Sports Activities From a Single Wrist-Worn Accelerometer: A Template-Matching-Based Approach | D53: Jenny Margarito | E53: https://doi.org/10.1109/TBME.2015.2471094 | F53: Aug | G53: 2015 | H53: SC | I53: N/A | K53: 20 | L53: 2 | M53: Philips DirectLife, Philips Consumer Lifestyle, Amsterdam, The Netherlands | N53: 48 | O53: 24 F, 24 M, age: 29 (9) yo. "The population included 29 normal weight subjects (16 females and 13 males, body mass index BMI = 22 kg/m2 on average) with a BMI below the threshold of 25 kg/m2 and 19 overweight subjects (8 females and 11 males, BMI = 27 kg/m2 on average) with a BMI higher than 25 kg/m2." | P53: Semi- or highly-supervised | Q53: N | R53: 8 | S53: cycling, cross trainer, rowing, running, squatting, stepping, walking, weight lifitng | T53: N/A | U53: N/A | V53: Euclidean, DTW, DDTW, RCE, DT, NB, LR, ANN | W53: Y | X53: N/A | Y53: Y | Z53: See Table 5 | AA53: 6 | AB53: 0 | AC53: SS. 50/50 for normal weight (no data from overweight population used in training) | AD53: Sensitivity | AE53: Table 5 | AF53: Y | AG53: N | AH53: N | AI53: N | AJ53: N | AL53: N | AM53: N | AN53: IP | AP53: N | AQ53: DNA | AS53: =IF(AND(AP53="N", ISBLANK(AQ53)), "THIS", "")
B54: 47 | C54: An Activity Recognition Framework Deploying the Random Forest Classifier and A Single Optical Heart Rate Monitoring and Triaxial Accelerometer Wrist-Band | D54: Saeed Mehrang | E54: https://doi.org/10.3390/s18020613 | F54: Feb | G54: 2018 | H54: SC | I54: N/A | K54: 25 | L54: 8 | M54: pulseOn CLOUD | N54: 25 (5 excluded) | O54: All male adults. 28.1 (3.8) yo, mean body mass index (BMI) of 24.8 (3.4) kg/m2 | P54: Semi- or highly-supervised | Q54: N | R54: 5 | S54: Sitting, Standing, Household activities, Stationary Cycling (high intensity), Stationary Cycling (low Intensity) | T54: See Table 1 | U54: D | V54: RF | W54: N | X54: R for preporcess, and Sklearn | Y54: Y | Z54: "From ACC signals, both time and frequency domain features were extracted. In the time domain, features were the mean and standard deviation of the absolute value of each axis. Absolute values were used since the subjects were wearing the device on either the left or right wrists depending on which one was their dominant hand. From the three ACC axes, signal magnitude area (SMA), mean, standard deviation, median, mean absolute deviation and the median absolute deviation of signal magnitude vector (SMV), as well as correlations between each pair of the three axes were calculated [6]. In the frequency domain, the relative energy of each axis in different frequency bands ((0 − 1], (1 − 2],(2 − 3],(3 − 4],(4 − 5],(5 − 6],(6 − 7],(7 − 8],(8 − 9],(9 − 10],(10 − 12.5) Hz) was computed for each window using short-time Fourier transform (STFT). In addition, the dominant frequency and its magnitude in the whole frequency range (0 − 12.5 Hz) of each axis in each window were computed" | AA54: 1 to 21 | AB54: 90 | AC54: LOSO CV | AD54: Accuracy | AE54: Sec. 4.3 | AF54: Y | AG54: N | AH54: N | AI54: N | AJ54: N | AL54: N | AM54: Y | AP54: N | AQ54: DNA | AS54: =IF(AND(AP54="N", ISBLANK(AQ54)), "THIS", "")
B55: 54 | C55: Sensor-based Complex Human Activity Recognition from Smartwatch Data using Hybrid Deep Learning Network | D55: Sakorn Mekruksavanich | E55: https://doi.org/10.1109/ITC-CSCC52171.2021.9501477 | F55: Aug | G55: 2021 | H55: DHA | I55: Y | K55: 10 | L55: N/A | M55: Apple Watch 2 | N55: 2 | O55: N/A | P55: Free-living | Q55: N | R55: 11 | S55: office working, reading, writing, taking a rest, playing a game, eating, cooking, dish washing, walking, running, raking transport | T55: "In workplaces, five tasks were considered: office work, reading, writing, sleeping, and playing a video game. Writing an email, writing a letter, and coding are all examples of office work. In kitchens, three things were considered: dining, cooking, and dish washing. The remaining three events were deemed suitable for outdoor participation." | U55: D | V55: CNN, LSTM, (their novel CNN with LSTM uses location data) | W55: Y | X55: Python v.3.6.9, TensorFlow v.2.2.0, Keras v.2.3.1, Scikit-Learn, Numpy v.1.18.5, and Pandas v.1.0.5 | Y55: N | AA55: 5, 10, 20, 30, 40s | AB55: N/A | AC55: 10-fold CV | AD55: Accuracy, F1, Precision, Recall | AE55: Table 2 | AF55: N | AG55: N | AH55: N | AI55: N | AJ55: N | AL55: N | AM55: N | AN55: IP | AP55: N | AQ55: TTS | AS55: =IF(AND(AP55="N", ISBLANK(AQ55)), "THIS", "")
B56: 124 | C56: RNN-based deep learning for physical activity recognition using smartwatch sensors: A case study of simple and complex activity recognition | D56: Sakron Mekruksavanich | E56: 10.3934/mbe.2022265 | F56: April | G56: 2022 | H56: WISDM | I56: Y | K56: 20 | L56: N/A | M56: LG G Watch | N56: 51 | O56: N/A | P56: Semi- or highly-supervised | Q56: Y | R56: 18 | S56: Walking, Jogging, Stairs, Sitting, Standing, Typing, Brushing Teeth, Eating Soup, Eating Chips, Eating Pasta, Drinking from Cup, Eating Sandwich, Kicking, Playing, Dribbling, Writing, Clapping, Folding Cloths, Walking, Jogging, Stairs, Sitting, Standing, Typing, Brushing Teeth, Eating Soup, Eating Chips, Eating Pasta, Drinking from Cup, Eating Sandwich, Kicking, Playing, Dribbling, Writing, Clapping, Folding Cloths | T56: N/A | U56: D | V56: CNN, LSTM, BiLSTM, GRU, BiGRU, Att-BiGRU | W56: Y | X56: Described in 4.1 | Y56: N | AA56: 10 | AB56: 0 or 50 | AC56: LOPO CV | AD56: Accuracy | AE56: Table 2 and 3 | AF56: N | AG56: Y | AH56: Y | AI56: N | AJ56: N | AL56: N | AM56: Y | AP56: Y | AS56: =IF(AND(AP56="N", ISBLANK(AQ56)), "THIS", "")
B57: 77 | C57: Recognizing and Understanding Sport Activities Based on Wearable Sensor Signals Using Deep Residual Network | D57: Sakorn Mekruksavanich | E57: https://doi.org/10.1109/RI2C60382.2023.10356022 | F57: Aug | G57: 2023 | H57: IM-Sporting Behaviors Dataset | I57: Y | K57: N/A | L57: N/A | M57: N/A | N57: N/A | O57: N/A | P57: N/A | Q57: N/A | R57: 6 | S57: table tennis, soccer, biking, badminton, basketball, and skipping | T57: N/A | U57: D | V57: ResNet (compared to other DL models). LSTM, CNN, BiLSTM, GRU, BiGRU | W57: Y | X57: N/A | Y57: N | AA57: N/A | AB57: 50 | AC57: 10-fold CV | AD57: Accuracy, Loss, F1 | AE57: Table 1 | AF57: N | AG57: Y | AH57: N | AI57: N | AJ57: N | AL57: N | AM57: N | AN57: IP | AP57: N | AQ57: TTS | AS57: =IF(AND(AP57="N", ISBLANK(AQ57)), "THIS", "")
B58: 107 | C58: Efficient Recognition of Complex Human Activities Based on Smartwatch Sensors Using Deep Pyramidal Residual Network | D58: Sakorn Mekruksavanich | E58: https://doi.org/10.1109/ICITEE59582.2023.10317707 | F58: Nov | G58: 2023 | H58: DHA | I58: Y | K58: 10 | L58: N/A | M58: Apple Watch | N58: 2 | O58: N/A | P58: Free-living | Q58: N | R58: 11 | S58: Office work, reading, writing, talking a rest, playing a game, eating, cooking, washing dishes, walking, running, taking transport | T58: N/A | U58: D | V58: 1D pyramid net. CNN, LSTM, BiLSTM, GRU, BiGRU | W58: Y | X58: N/A | Y58: N | AA58: 10 | AB58: 50 | AC58: N/A | AD58: Accuracy, F1, Loss | AE58: Table 2 | AF58: Y | AG58: N | AH58: N | AI58: N | AJ58: N | AL58: N | AM58: N | AN58: IP | AP58: N | AQ58: TTS | AS58: =IF(AND(AP58="N", ISBLANK(AQ58)), "THIS", "")
B59: 104 | C59: Deep Learning Networks for Complex Activity Recognition Based on Wrist-Worn Sensor | D59: Sakorn Mekruksavanich | E59: https://doi.org/10.1109/TENCON58879.2023.10322430 | F59: Nov | G59: 2023 | H59: WHARF | I59: Y | K59: 32 | L59: N/A | M59: N/A | N59: 16 | O59: 11 M, 5 F, 19-81 yo | P59: N/A | Q59: N/A | R59: 14 | S59: Clean teeth, comb hair, rise from the bed, lie down on the bed, sit down on a chair, stand up from a chair, sip from a glass, dine with utensils, eat with spoon, pour water into a glass, make a telephone call, climb the stairs,descend the stairs, walk | T59: N/A | U59: R | V59: CNN, LSTM, BiLSTM, GRU, BiGRU, CNN-BI-GRU | W59: Y | X59: Python, TF, Keras, Scikit learn, Numpy, and Pandas | Y59: N | AA59: 3 | AB59: 50 | AC59: 5-fold CV | AD59: Accuracy, F1, Loss | AE59: Table 2 | AF59: Y | AG59: N | AH59: N | AI59: N | AJ59: N | AL59: N | AM59: N | AN59: IP | AP59: N | AQ59: TTS | AS59: =IF(AND(AP59="N", ISBLANK(AQ59)), "THIS", "")
B60: 139 | C60: Effect of Sliding Window Sizes on Sensor-Based Human Activity Recognition Using Smartwatch Sensors and Deep Learning Approaches | D60: Sakorn Mekruksavanich | E60: 10.1109/IBDAP62940.2024.10689691 | F60: Aug | G60: 2024 | H60: DHA | I60: Y | K60: 10 | L60: N/A | M60: Apple Watch 2 | N60: 2 | O60: N/A | P60: Free-living (4 week protocol) | Q60: N | R60: 11 | S60: Office work, Reading, Writing, Taking a rest, Playing a game, Eating, Cooking, Washing dishes, Walking, Running, Taking a transport | T60: N/A | U60: N/A | V60: CNN, LSTM, BiLSTM, CNN-LSTM | W60: Y | X60: N/A | Y60: N | AA60: Variable. 5, 10, 20, 30, and 40 | AB60: 0, 50 | AC60: N/A | AD60: Accuracy, Precision, Recall, F1 | AE60: Table II (non-overlapping windows) and Table III (50% overlap) | AF60: N | AG60: N | AH60: N | AI60: N | AJ60: N | AL60: N | AM60: N | AN60: IP | AP60: N | AQ60: ANR | AS60: =IF(AND(AP60="N", ISBLANK(AQ60)), "THIS", "")
B61: 143 | C61: A Deep Hybrid Neural Network for Efficient Human Activity Recognition Based on Accelerometer Data from Wristband | D61: Sakorn Mekruksavanich | E61: 10.1109/ICSESS67729.2025.11380320 | F61: Dec | G61: 2025 | H61: TWristAR | I61: Y | K61: N/A | L61: N/A | M61: Empatica E4 | N61: 3 | O61: N/A | P61: Semi- or highly-supervised | Q61: N | R61: 6 | S61: walking, walking upstairs, walking downstairs, jogging, sitting, standing | T61: N/A | U61: R | V61: CNN-CBAM-BiGRU (theirs), CNN, LSTM, BiLSTM, GRU, BiGRU | W61: Y | X61: Python 3.6.9, TensorFlow 2.2.0, Keras 2.3.1, Scikit-Learn 0.23.2, NumPy 1.18.5, Pandas 1.0.5, and Matplotlib 3.2.2 | Y61: N | AA61: 3 | AB61: 50 | AC61: 5-fold CV | AD61: Accuracy, Precision, Recall, F1 | AE61: Table 1 | AF61: Y (Fig 5) | AG61: N | AH61: N | AI61: N | AJ61: N | AL61: N | AM61: N | AN61: IP | AP61: N | AQ61: ANR | AS61: =IF(AND(AP61="N", ISBLANK(AQ61)), "THIS", "")
B62: 108 | C62: Evaluating the Impact of a Two-Stage Multivariate Data Cleansing Approach to Improve to the Performance of Machine Learning Classifiers: A Case Study in Human Activity Recognition | D62: Dionicio Neira-Rodado | E62: https://doi.org/10.3390/s20071858 | F62: Mar | G62: 2020 | H62: Cleland | I62: Y | K62: 51.2 | L62: N/A | M62: Shimmer | N62: N/A | O62: N/A | P62: Semi- or highly-supervised | Q62: Y | R62: 18 | S62: See Table 2 | T62: See Table 2 | U62: D | V62: KNN, SVM, RF, NN, and Regression | W62: Y | X62: R and WEKA | Y62: Y | Z62: See Table 3 | AA62: 4 | AB62: 0 | AC62: 10-fold CV (with 66/34 split in folds) | AD62: F1 | AE62: Table 5, 6, 7 | AF62: N | AG62: N | AH62: N | AI62: N | AJ62: N | AL62: N | AM62: N | AN62: IP | AP62: N | AQ62: TTS | AS62: =IF(AND(AP62="N", ISBLANK(AQ62)), "THIS", "")
B63: 106 | C63: Design and assessment of the data analysis process for a wrist-worn smart object to detect atomic activities in the smart home | D63: Qin Ni | E63: https://doi.org/10.1016/j.pmcj.2019.03.006 | F63: May | G63: 2019 | H63: SC | I63: N/A | K63: N/A | L63: N/A | M63: N/A | N63: 10 | O63: "Healthy" adults | P63: Semi- or highly-supervised | Q63: N | R63: 12 | S63: Clean teeth, comb hair, rise from the bed, lie down on the bed, sit down on a chair, stand up from a chair, sip from a glass, dine with utensils, eat with spoon, pour water into a glass, make a telephone call, climb the stairs,descend the stairs, walk | T63: See Table 1 | U63: L | V63: RF, KNN, J48, MLP, NB, SVM | W63: Y | X63: WEKA + MATLAB | Y63: Y | Z63: See Table 2 | AA63: 256 (samples, no reported s) | AB63: 50 | AC63: 10-fold CV | AD63: Accuracy, F1, MAE, ROC, Sensitivitiy, Specificity | AE63: Table 5, 7, 8 | AF63: Y | AG63: N | AH63: N | AI63: N | AJ63: N | AL63: N | AM63: N | AN63: IP | AP63: N | AQ63: DNA | AS63: =IF(AND(AP63="N", ISBLANK(AQ63)), "THIS", "")
B64: 149 | C64: Language of actions: A generative model for activity recognition and next move prediction from motion sensors | D64: Hasan Ogul | E64: https://doi.org/10.1016/j.eswa.2024.125947 | F64: Nov | G64: 2024 | H64: HMP | I64: Y | K64: 32 | L64: 3 | M64: N/A | N64: 16 | O64: N/A | P64: Semi- or highly-supervised | Q64: N/A | R64: 8 | S64: getting up from bed, sitting down and standing up from a chair, climbing the stairs, walking, drinking and pouring water, and eating | T64: N/A | U64: R | V64: VLMC | W64: Y (They compare solely against other results from other papers. Results may not be directly compared.) | X64: N/A | Y64: N (they use a action move dictionary which can be akin to features) | AA64: N/A | AB64: N/A | AC64: 10-fold CV | AD64: Accuracy | AE64: Table 3 | AF64: N (they include classwise evaluations just not of wrist only) | AG64: N | AH64: Y | AI64: N | AJ64: N | AL64: N | AM64: N | AN64: IF | AP64: N | AQ64: ANR | AS64: =IF(AND(AP64="N", ISBLANK(AQ64)), "THIS", "")
B65: 35 | C65: Building robust models for Human Activity Recognition from raw accelerometers data using Gated Recurrent Units and Long Short Term Memory Neural Networks | D65: Jeremiah Okai | E65: https://doi.org/10.1109/EMBC.2019.8857288 | F65: Jul | G65: 2019 | H65: GOTOv | I65: Y | K65: 83 | L65: 8 | M65: GENEActiv | N65: 35 | O65: 14 F, 21 M, avg. age 65 | P65: Semi- or highly-supervised | Q65: Y | R65: 16 | S65: lying down, sitting, standing and several household chores, such as dishwashing, stakingShelves and vacuumCleaning. The outdoor activities included the different types of walking: walking Slow, walking Normal, walking Fast and cycling | T65: N/A | U65: N/A | V65: RNN with LSTM + GRU | W65: Y | X65: N/A | Y65: N | AA65: 2.5 | AB65: N/A | AC65: LOSO CV | AD65: Accuracy | AE65: Fig. 1 and 2 | AF65: Y | AG65: Y | AH65: N | AI65: N | AJ65: N | AL65: N | AM65: N | AN65: IP | AP65: N | AQ65: ANR | AS65: =IF(AND(AP65="N", ISBLANK(AQ65)), "THIS", "")
B66: 70 | C66: An Approach towards Position-Independent Human Activity Recognition Model based on Wearable Accelerometer Sensor | D66: Naima Qamar | E66: https://doi.org/10.1016/j.procs.2020.10.028 | F66: Nov | G66: 2020 | H66: PAMAP2 | I66: Y | K66: 100 | L66: N/A | M66: N/A | N66: 9 | O66: 1F, 8M, 25-30 yo | P66: Semi- or highly-supervised | Q66: N/A | R66: 11 | S66: lying (a1), sitting (a2), standing (a3), ironing (a4), vacuuming (a5), walking upstairs (a6), walking downstairs (a7), ascend stairs (a8), descend stairs (a9), cycling (a10), and running (a11) | T66: N/A | U66: N/A | V66: RF, SVM-SMO, KNN, BN, J48 | W66: Y | X66: N/A | Y66: Y | Z66: See Table 1 | AA66: 5 | AB66: 0 | AC66: 5-fold CV | AD66: Accuracy, F1, Precision, Sensitivity | AE66: Table 1 | AF66: Y | AG66: Y | AH66: N | AI66: N | AJ66: N | AL66: N | AM66: N | AN66: IP | AP66: N | AQ66: TTS | AS66: =IF(AND(AP66="N", ISBLANK(AQ66)), "THIS", "")
B67: 57 | C67: A Transformer Based Approach for Activity Detection | D67: Gulshan Sharma | E67: https://doi.org/10.1145/3503161.3551598 | F67: Oct | G67: 2022 | H67: harAGE | I67: Y | K67: 25 | L67: N/A | M67: N/A | N67: N/A | O67: N/A | P67: N/A | Q67: N/A | R67: 8 | S67: cycling, laying, running, sitting, stair climbing, standing, walking, and, washing hands | T67: N/A | U67: N/A | V67: 1D+ 2D CNNS. Transformer Network | W67: Y | X67: TensorFlow | Y67: N | AA67: 20 | AB67: N/A | AC67: N/A | AD67: Macro Recall | AE67: Table 1 | AF67: Y | AG67: Y | AH67: N | AI67: N | AJ67: N | AL67: N | AM67: N | AN67: IS | AP67: N | AQ67: TTS | AS67: =IF(AND(AP67="N", ISBLANK(AQ67)), "THIS", "")
B68: 68 | C68: An adaptive time window method for human activity recognition | D68: Zhang Sheng | E68: https://doi.org/10.1109/CCECE.2015.7129445 | F68: May | G68: 2015 | H68: SC | I68: N/A | K68: 50 | L68: 8 | M68: iNemo sensor module (STEVAL-MKI062) | N68: N/A | O68: N/A | P68: N/A | Q68: N/A | R68: 6 | S68: upstairs, downstairs, standing, walking, running, sitting | T68: N/A | U68: N/A | V68: C4.5 DT | W68: N | X68: WEKA | Y68: Y | Z68: "Using the data in a time window as an instance we extract features including mean of the acceleration in three axes, the correlation between three axes, and the spectrum energy" | AA68: Adaptive | AB68: Adaptive | AC68: 10-fold CV | AD68: AUC ROC, FPR, Precision, Recall | AE68: Fig. 4 | AF68: Y | AG68: N | AH68: N | AI68: N | AJ68: N | AL68: N | AM68: Y | AP68: N | AQ68: DNA | AS68: =IF(AND(AP68="N", ISBLANK(AQ68)), "THIS", "")
B69: 121 | C69: Mobile sensor based human activity recognition: distinguishing of challenging activities by applying long short-term memory deep learning modified by residual network concept | D69: Seyed Vahab Shojaedini | E69: 10.1007/s13534-020-00160-x | F69: June | G69: 2020 | H69: WISDM | I69: Y | K69: 20 | L69: N/A | M69: N/A | N69: 51 | O69: N/A | P69: Semi- or highly-supervised | Q69: Y | R69: 8 | S69: walking, jogging, stairs, standing, sitting, eating soup, eating sandwhich, eating chips | T69: N/A | U69: N/A | V69: CNN, ConvLSTM, and ConvLSTM+ResNet | W69: Y | X69: TF | Y69: N | Z69: N | AA69: "a window length of 90" (90 s or 4.5 s) | AB69: 50 | AC69: N/A | AD69: Accuracy | AE69: Tables 4, 6, 8 | AF69: Y | AG69: N | AH69: Y | AI69: N | AJ69: N | AL69: N | AM69: Y | AP69: N | AQ69: TTS | AS69: =IF(AND(AP69="N", ISBLANK(AQ69)), "THIS", "")
B70: 140 | C70: Transportation Mode Recognition Based on Low-Rate Acceleration and Location Signals With an Attention-Based Multiple-Instance Learning Network | D70: Christos Siargkas | E70: 10.1109/TITS.2024.3387834 | F70: Apr | G70: 2024 | H70: SHL (Preview) | I70: Y | K70: 10 (downsampled from 100) | L70: N/A | M70: N/A | N70: 3 | O70: N/A | P70: Free-living (3 day protocol) | Q70: N | R70: 8 | S70: still, walk, run, bike, car, bus, train, and subway | T70: N/A | U70: N/A | V70: ANN | W70: Y | X70: N/A | Y70: N | AA70: 60 | AB70: N/A (used in some features) | AC70: LOSO CV. (80/20 split within participants) | AD70: Accuracy, F1 | AE70: Table I | AF70: N (they include classwise evaluations just not of wrist only) | AG70: Y | AH70: N | AI70: N | AJ70: N | AL70: N | AM70: N | AN70: IS | AP70: N | AQ70: TTS | AS70: =IF(AND(AP70="N", ISBLANK(AQ70)), "THIS", "")
B71: 114 | C71: Improving the classification accuracy of streaming data using SAX similarity features | D71: Pekka Siirtola | E71: https://doi.org/10.1016/j.patrec.2011.06.025 | F71: Oct | G71: 2011 | H71: SC | I71: N/A | K71: 100 | L71: N/A | M71: Accelerometer from VTI technologies | N71: 7 | O71: "Healthy" | P71: Semi- or highly-supervised | Q71: Y | R71: 5 | S71: roller skating, aerobics, walking, running, and Nordic walking. | T71: N/A | U71: L | V71: kNN, LDA, QDA, C4.5 and naive Bayes. | W71: Y | X71: N/A | Y71: Y | Z71: See Table 1 | AA71: 2 | AB71: 25 | AC71: N/A | AD71: Accuracy | AE71: Fig. 6, Table 3, 4 | AF71: N | AG71: N | AH71: Y | AI71: N | AJ71: N | AL71: N | AM71: Y | AP71: N | AQ71: DNA | AS71: =IF(AND(AP71="N", ISBLANK(AQ71)), "THIS", "")
B72: 93 | C72: Smart Devices are Different: Assessing and Mitigating Mobile Sensing Heterogeneities for Activity Recognition | D72: Allan Stisen | E72: https://doi.org/10.1145/2809695.2809718 | F72: Nov | G72: 2015 | H72: SC | I72: Y | J72: https://cs.au.dk/~allans/heterogenity/ | K72: 200 and 100 | L72: N/A | M72: LG G and Samsung Galaxy Gear | N72: 9 | O72: 25-30 yo | P72: N/A | Q72: N/A | R72: 6 | S72: ‘Biking’, ‘Sitting’, ‘Standing’, ‘Walking’, ‘Stair Up’ and ‘Stair down’ | T72: N/A | U72: B | V72: C4.5 decision tree, linear support vector machines, K-nearest neighbor, and random forest ensemble learner. | W72: Y | X72: N/A | Y72: Y | Z72: See Table 2 and 3. | AA72: 2 | AB72: 50 | AC72: 10-fold, LOSO CV, leave-one-(watch)model-out CV | AD72: Weighted F1 | AE72: Figure 7 | AF72: N | AG72: Y | AH72: N | AI72: N | AJ72: N | AL72: N | AM72: N | AN72: IP | AP72: N | AQ72: TTS | AR72: NOTE: LOSO may be reproducible. | AS72: =IF(AND(AP72="N", ISBLANK(AQ72)), "THIS", "")
B73: 136 | C73: Ngram time series model to predict activity type and energy cost from wrist, hip and ankle accelerometers: implications of age | D73: Scott J Strath | E73: 10.1088/0967-3334/36/11/2335 | F73: Oct | G73: 2015 | H73: SC | I73: N/A | K73: N/A | L73: N/A | M73: Actigraph GT3x | N73: 99 | O73: See Table 1 | P73: Semi- or highly-supervised | Q73: Y | R73: 8 (from 12) | S73: slow walk, walk, fast walk, computer work, vacuuming, sweeping/mopping, carrying boxes, walking with intermittent stair climbing | T73: N/A | U73: ND | V73: SVM | W73: N/A | X73: N/A | Y73: Y | Z73: See Sec. Data processing: physical activity accelerometer—Ngram-based feature representation (Fig 1) | AA73: N/A | AB73: N/A | AC73: LOSO CV | AD73: Accuracy | AE73: Table 3 | AF73: Y | AG73: Y | AH73: N | AI73: N | AJ73: N | AL73: N | AM73: N | AN73: IS | AP73: N | AQ73: DNA | AS73: =IF(AND(AP73="N", ISBLANK(AQ73)), "THIS", "")
B74: 74 | C74: CapsGaNet: Deep Neural Network Based on Capsule and GRU for Human Activity Recognition | D74: Xiaojie Sun | E74: https://doi.org/10.1109/JSYST.2022.3153503 | F74: Mar | G74: 2022 | H74: SC (DAAD) | I74: N/A | K74: 20 | L74: N/A | M74: SDUISv1 | N74: 12 | O74: 6 M, 6 F, 24-34 yo | P74: N/A | Q74: N | R74: 8 | S74: handclap, running, sitting, walking, waving, punching down, punching straight, and slapping. | T74: N/A | U74: R | V74: SVM, CNN, GRU, CApsNEt, CApsGaNET | W74: Y | X74: TensorFlow-gpu 1.11.0 | Y74: N | AA74: 4 | AB74: 50 | AC74: SS. 75/25 | AD74: Accuracy, F1, Precision, Recall | AE74: Table 7 | AF74: Y | AG74: N | AH74: Y | AI74: N | AJ74: N | AL74: N | AM74: N | AN74: IP | AP74: N | AQ74: DNA | AS74: =IF(AND(AP74="N", ISBLANK(AQ74)), "THIS", "")
B75: 49 | C75: On-body localization of wearable devices: An investigation of position-aware activity recognition | D75: Timo Sztyler | E75: https://doi.org/10.1109/PERCOM.2016.7456521 | F75: Mar | G75: 2016 | H75: SC (Realworld HAR) | I75: Y | K75: 50 | L75: N/A | M75: LG G Watch R | N75: 15 | O75: 31.9 (12.4) yo, 173.1 (6.9) cm, 74.1 (13.8) kg, 8 M, 7 F | P75: Semi- or highly-supervised | Q75: N | R75: 8 | S75: climbing stairs down (A1) and up (A2), jumping (A3), lying (A4), standing (A5), sitting (A6), running/ jogging (A7), and walking (A8) | T75: N/A | U75: L | V75: RF | W75: N | X75: N/A | Y75: Y | Z75: See Table 1 | AA75: 1 | AB75: 50 | AC75: 10-fold CV | AD75: F1, FP rate, Precision, Recall | AE75: Table 2 and 9 | AF75: Y | AG75: Y | AH75: N | AI75: N | AJ75: Y* (only feature extraction, not full algorithm) | AK75: https://github.com/sztyler/sensorfeatureextraction | AL75: N | AM75: N | AN75: IP | AP75: N | AQ75: TTS | AS75: =IF(AND(AP75="N", ISBLANK(AQ75)), "THIS", "")
B76: 100 | C76: Position-aware activity recognition with wearable devices | D76: Timo Sztyler | E76: https://doi.org/10.1016/j.pmcj.2017.01.008 | F76: Jul | G76: 2017 | H76: RealWorld HAR | I76: Y | K76: 50 | L76: N/A | M76: LG G watch R | N76: 15 | O76: 31.9 (12.4) yo, 173.1 (6.9) cm, weight 74.1 (13.8) kg, 8 M, 7 F | P76: N/A | Q76: N | R76: 8 | S76: stairs down (A1) and up (A2), jumping (A3), lying (A4), standing (A5), sitting (A6), running/jogging (A7), and walking (A8) | T76: N/A | U76: N/A | V76: RF | W76: N | X76: N/A | Y76: Y | Z76: See Table 1 | AA76: 1 | AB76: 50 | AC76: Randomly, LOSO CV, TopPairs CV, and Physical CV | AD76: F1 | AE76: Table 9, 10 | AF76: Y | AG76: Y | AH76: N | AI76: N | AJ76: Y* (only feature extraction, not full algorithm) | AK76: https://github.com/sztyler/sensorfeatureextraction | AL76: N | AM76: N | AN76: IP | AP76: N | AQ76: TTS | AR76: NOTE: LOSO may be reproducible. | AS76: =IF(AND(AP76="N", ISBLANK(AQ76)), "THIS", "")
B77: 141 | C77: Quantum-based Gated Recurrent Units for Multiclass Classification to Monitor Daily Living Activities for Early Disease Detection | D77: Bao-Nhi Dang Tran | E77: 10.1109/HealthCom60970.2024.10880739 | F77: Nov | G77: 2024 | H77: WHARF | I77: Y | K77: 32 | L77: N/A | M77: N/A | N77: N/A | O77: N/A | P77: Semi- or highly-supervised | Q77: N, but they applied techniques to handle the imbalance. | R77: 8 (grouped from 14 raw activities) | S77: Get up & lay down, walk, eat & drink, stairs, telephone, sit down & stand up, brush teeth, comb hair | T77: N/A | U77: R | V77: QGRU-MC | W77: N | X77: Python and Pennylane library | Y77: Y | Z77: "mean, median, standard deviation, interquartile range, and correlation among the three axes over each of these fixedlength windows, without any overlap between adjacent windows" | AA77: 180 | AB77: 0 | AC77: SS. 80 (80/20 train/validatation) / 20 split | AD77: Accuracy, F1, Precision, and Recall | AE77: Table II | AF77: Y (Fig 5) | AG77: N | AH77: N | AI77: N | AJ77: N | AL77: N | AM77: N | AN77: IP | AP77: N | AQ77: ANR | AS77: =IF(AND(AP77="N", ISBLANK(AQ77)), "THIS", "")
B78: 18 | C78: An Improved Activity Recognition Method Based on Smart Watch Data | D78: Dengpan Tian | E78: https://doi.org/10.1109/CSE-EUC.2017.148 | F78: Jul | G78: 2017 | H78: SC | I78: N/A | K78: 50 | L78: N/A | M78: iGwatch by Qingdao iGuan Technology | N78: 10 | O78: N/A | P78: N/A | Q78: N/A | R78: 5 | S78: Standing, walking, running, upstiars, downstairs | T78: N/A | U78: N/A | V78: DT | W78: N | X78: MATLAB (CART alg) | Y78: Y | Z78: "mean value, standard deviation, kurtosis, peak-to-peak value of X, Y, Z, \alpha and \gamma in each window" (Sec IV.B) | AA78: 4 | AB78: 50 | AC78: N/A | AD78: Accuracy | AE78: Table 2 | AF78: Y | AG78: N | AH78: N | AI78: N | AJ78: N | AL78: N | AM78: N | AN78: IP | AP78: N | AQ78: DNA | AS78: =IF(AND(AP78="N", ISBLANK(AQ78)), "THIS", "")
B79: 48 | C79: Selective Ensemble Based on Extreme Learning Machine for Sensor-Based Human Activity Recognition | D79: Yiming Tian | E79: https://doi.org/10.3390/s19163468 | F79: Aug | G79: 2019 | H79: SC | I79: N/A | K79: 150 | L79: 6 | M79: TRIGNO | N79: 5 | O79: "healthy students" 20-34 yo, mean age: 26, 3 M, 2 F | P79: Semi- or highly-supervised | Q79: N/A | R79: 6 | S79: walking, running, going upstairs, going downstairs, jumping and standing. | T79: N/A | U79: L | V79: DMGSOSEN ensemble method with 50, 100, 150, and 200 different pools to classify (ensemble models are best on ELMS (extreme leearning models)) | W79: Y | X79: MATLAB | Y79: Y | Z79: "These features include the maximum, the minimum, the mean value, standard deviation σ, skewness S, kurtosis K, correlation coefficient C between three axes, signal magnitude area (SMA), and number of zero crossings which is number of zero crossings in a window after subtracting the window mean value from every window sample." | AA79: 2 | AB79: 50 | AC79: LOSO CV | AD79: Accuracy, F1 | AE79: Table 2-5 | AF79: Y | AG79: N | AH79: N | AI79: N | AJ79: N | AL79: N | AM79: Y | AP79: N | AQ79: DNA | AS79: =IF(AND(AP79="N", ISBLANK(AQ79)), "THIS", "")
B80: 72 | C80: A Novel Sensor-Based Human Activity Recognition Method Based on Hybrid Feature Selection and Combinational Optimization | D80: Yiming Tian | E80: https://doi.org/10.1109/ACCESS.2021.3100580 | F80: Jul | G80: 2021 | H80: SC | I80: N/A | K80: 150 | L80: 6 | M80: TRIGNOTM wireless system from Delsys Company | N80: 10 | O80: 20-45 yo | P80: Semi- or highly-supervised | Q80: N/A | R80: 6 | S80: walking (W), going upstairs (GU), going downstairs (GD), running (R), jumping (J) and one static activity standing (S). | T80: N/A | U80: L | V80: Kernel extreme learning machine (KELM) | W80: Y | X80: MATLAB | Y80: Y | Z80: See Table 1 | AA80: 2 | AB80: 50 | AC80: LOSO CV | AD80: Accuracy, F1, Precision, Recall | AE80: Table 11 | AF80: Y | AG80: Y | AH80: N | AI80: N | AJ80: N | AL80: N | AM80: Y | AP80: N | AQ80: DNA | AS80: =IF(AND(AP80="N", ISBLANK(AQ80)), "THIS", "")
B81: 92 | C81: Human activity recognition based on random forests | D81: Lu Xu | E81: https://doi.org/10.1109/FSKD.2017.8393329 | F81: Jul | G81: 2017 | H81: SC | I81: N/A | K81: 62 | L81: N/A | M81: Microsoft band 2 | N81: 2 | O81: N/A | P81: Free-living | Q81: Y | R81: 6 | S81: walking, upstairs, downstiars, jumpting, running, keeping static | T81: N/A | U81: N/A | V81: DT (trained on CART), FNN, RF with various numbers of trees | W81: Y | X81: N/A | Y81: N/A | AA81: ~1 | AB81: 50 | AC81: SS. 65/35 | AD81: Accuracy | AE81: Fig. 2, 4, 6 | AF81: Y | AG81: N | AH81: N | AI81: N | AJ81: N | AL81: N | AM81: Y | AP81: N | AQ81: DNA | AS81: =IF(AND(AP81="N", ISBLANK(AQ81)), "THIS", "")
B82: 60 | C82: Activity Recognition Using One-Versus-All Strategy with Relief-F and Self-Adaptive Algorithm | D82: M. N Shah Zainudin | E82: https://doi.org/10.1109/ICOS.2018.8632818 | F82: Nov | G82: 2018 | H82: PAMAP2 | I82: Y | K82: N/A | L82: N/A | M82: N/A | N82: 9 | O82: 1 F, 8 M, all employed, 27.22 (3.31) yo, average body mass index (BMI) ranging from 25.11 ± 2.62kg. | P82: Semi- or highly-supervised | Q82: N/A | R82: 18 | S82: Lying, sitting, standing, walking, running, nordic walk, watch tv, comp work, car driving, ascending, descending, vacuum, ironing, folding, cleaning, play soccer, jump rope | T82: N/A | U82: D | V82: RF | W82: N | X82: N/A | Y82: Y | Z82: "Subsequently, additional features are extracted from each window segment to describe the activity characteristic. Extracted features are expected to represent the relevant iN/Aormation by reducing the representation of data stream. In such states, the features from two groups: statistical and frequency features are derived. " | AA82: N/A | AB82: 50 | AC82: SS: 70/30. 10-fold CV in training; holdout strategy used for evaluation | AD82: Accuracy | AE82: Table 2, 3 | AF82: Y | AG82: Y | AH82: N | AI82: N | AJ82: N | AL82: N | AM82: N | AN82: IF | AP82: N | AQ82: TTS | AS82: =IF(AND(AP82="N", ISBLANK(AQ82)), "THIS", "")
B83: 145 | C83: An enhanced dual inception-attention-BiGRU-attention model integrating wavelet transform for wearable sensor-based human activity recognition | D83: Xingao Zhang | E83: 10.1038/s41598-025-32859-1 | F83: Dec | G83: 2025 | H83: SC (WSMC-HAR) | I83: Y | J83: Available upon request. | K83: 20 | L83: 2 | M83: MPU6050 | N83: 7 | O83: All males. "Mean age of 21 ±3 years, a mean weight of 66 ±14 kg, and a mean height of 175 ±20 cm." | P83: Semi- or highly-supervised | Q83: N | R83: 5 | S83: upstairs, downstairs, sitting, running, jogging | T83: N/A | U83: N/A | V83: Dual-INABA (theirs), CNN, CNN-LSTM, LSTM-RNN, Multi-Channel CNN-CRU, Multi-input CNN-GRU, iSPIception, Inception-GRU-Attention | W83: Y | X83: "TensorFlow in version 2.9.0, a widely acclaimed deep learning network, alongside Pandas version 2.0.3 and NumPy version 1.24.3 for data manipulation and numerical computations." | Y83: N | AA83: N/A | AB83: N/A | AC83: SS. 70/20/10 | AD83: Accuracy, Recall, Precision, F1 | AE83: Table 4 , 6, 7 (their model), 8, 9 | AF83: Y (Fig 12) | AG83: N | AH83: Y | AI83: N | AJ83: Y | AK83: https://github.com/Mongoman1021/Dual-INABA-and-WSMC-HAR | AL83: N | AM83: Y | AP83: Y | AR83: Data must be requested. | AS83: =IF(AND(AP83="N", ISBLANK(AQ83)), "THIS", "")
B84: 45 | C84: Human Activity Recognition Based on Motion Sensor Using U-Net | D84: Yong Zhang | E84: https://doi.org/10.1109/ACCESS.2019.2920969 | F84: Jun | G84: 2019 | H84: SC | I84: Y | K84: 25 | L84: N/A | M84: N/A | N84: N/A | O84: Sanitation workers | P84: N/A | Q84: N | R84: 7 | S84: Walk, Run, Sweep, Bsweep, Clean, Dump and Daily activities | T84: Walk, Run, Sweep, Bsweep (sweep using a big broom), Clean, Dump and Daily activities (like sitting and smoking) | U84: N/A | V84: U net (they compared against a lot of other models SVM, DT, CNN, LSTM, ConvLSTM, FCN, Segnet, mask RCNN) | W84: Y | X84: TensorFlow and Keras | Y84: Y | Z84: "Both WISDM dataset and HAPT dataset include the raw data and the extracted features data. 242 features from OPP Gesture dataset and 57 features from Sanitation dataset are extracted manually, including the means, variances and so on. The extracted features datasets are available online." | AA84: 96 samples | AB84: 0 | AC84: SS. 49/21/30 (70% of data used for training seperated into a 70/30 train/validation set) | AD84: Accuracy, WF1 | AE84: Table 2 | AF84: Y | AG84: N | AH84: Y | AI84: N | AJ84: Y | AK84: https://github.com/zhangzhao156/Human-Activity-Recognition-Codes-Datasets | AL84: N | AM84: Y | AP84: N | AQ84: TTS | AS84: =IF(AND(AP84="N", ISBLANK(AQ84)), "THIS", "")
B85: 29 | C85: Comparison of Data Preprocessing Approaches for Applying Deep Learning to Human Activity Recognition in the Context of Industry 4.0 | D85: Xiaochen Zheng | E85: https://doi.org/10.3390/s18072146 | F85: Jun | G85: 2018 | H85: RealWorld HAR | I85: Y | K85: 50 | L85: N/A | M85: N/A | N85: 15 | O85: 31.9 (12.4) yo, 173.1 (6.9) cm, and weight 74.1 ± 13.8, with eight males and seven females) | P85: Semi- or highly-supervised | Q85: N | R85: 8 | S85: climbing stairs down (A1), climbing stairs up (A2), jumping (A3), lying (A4), jogging (A5), standing (A6), sitting (A7), and walking (A8) | T85: N/A | U85: N/A | V85: CNN | W85: N | X85: TensorFlow | Y85: Y (for some experiments) | Z85: See Table 1 | AA85: 10.24 | AB85: 0 (can vary for spectorograms). See Sec. 3.2 | AC85: SS. 90/10 by participant | AD85: Accuracy | AE85: Figure 7 | AF85: N (they include classwise evaluations just not of wrist only) | AG85: N | AH85: N | AI85: N | AJ85: Y | AK85: https://www.researchgate.net/publication/317180890_Step-by-step_introduction_to_acceleration_data_classification_using_deep_learning_methods | AL85: N | AM85: Y | AP85: N | AQ85: TTS | AS85: =IF(AND(AP85="N", ISBLANK(AQ85)), "THIS", "")
B86: 113 | C86: A Human Activity Recognition Model Based on Wearable Sensor | D86: Fan Zhou | E86: https://doi.org/10.1109/ICDH57206.2022.00033 | F86: Oct | G86: 2022 | H86: SC | I86: N/A | K86: N/A | L86: N/A | M86: N/A | N86: N/A | O86: N/A | P86: N/A | Q86: Y | R86: 8 | S86: Sit, stand, fo slow, go fast, upstairs, downstairs, jog, run fast | T86: N/A | U86: N/A | V86: CNN, RNN, and ConvRNN. Also SVM, DT, RF | W86: Y | X86: N/A | Y86: Y | Z86: signal magnitude | AA86: 2 | AB86: N/A | AC86: N/A | AD86: F1, Precision, Recall | AE86: Table 3, 4 | AF86: Y | AG86: N | AH86: N | AI86: N | AJ86: N | AL86: N | AM86: N | AN86: IP | AP86: N | AQ86: DNA | AS86: =IF(AND(AP86="N", ISBLANK(AQ86)), "THIS", "")
A87: Personalized HAR | B87: 26 | C87: Personalized Activity Recognition with Deep Triplet Embeddings | D87: David Burns | E87: https://doi.org/10.3390/s22145222 | F87: July | G87: 2022 | H87: WISDM | I87: Y | K87: 50 (upsampled from 20) | L87: N/A | M87: Android smartwatch | N87: 47 (51 were collected but four were excluded due to data issues during collection) | O87: N/A | P87: N/A | Q87: N | R87: 18 | S87: Walking, jogging, ascending/descending stairs, sitting, standing, kicking a soccer ball, dribbling a basketball, catching a tennis ball, typing, writing, clapping, brushing teeth, folding clothes, eating pasta, eating soup, eating a sandwich, eating chips, drinking from a cup | T87: N/A | U87: N/A | V87: fully-convolutional neural network (FCN), personalized engineered feature model (PEF), personalized deep feature model (PDF), personalized triplet network trained with conventional triplet loss (PTN†), and the personalized triplet model trained with patient-specific triplet loss (PTN) | W87: Y | X87: Keras, Seglearn, and Scikit-learn | Y87: Y (for baseline algorithms) | Z87: "mean, median, absolute energy, standard, deviation, variance, minimum, maximum, skewness, kurtosis, mean spectral energy, and mean crossings. The features are individually computed for each of the data channels in the dataset. All features are individually scaled to unit norm and zero mean across the training dataset." | AA87: 10 | AB87: 80 | AC87: 5-fold CV | AD87: Accuracy | AE87: Table 2 | AF87: N | AG87: N | AH87: N | AI87: N | AJ87: Y | AK87: https://github.com/dmbee/fcn-core | AL87: N | AM87: Y | AP87: N | AQ87: TTS | AS87: =IF(AND(AP87="N", ISBLANK(AQ87)), "THIS", "")
B88: 122 | C88: Activity Recognition Using Community Data to Complement Small Amounts of Labeled Instances | D88: Enrique Garcia-Ceja | E88: 10.3390/s16060877 | F88: June | G88: 2016 | H88: WHARF | I88: Y | K88: 32 | L88: N/A | M88: N/A | N88: 16 | O88: N/A | P88: Semi- or highly-supervised | Q88: N | R88: 12 | S88: (1) brush teeth; (2) climb stairs; (3) comb hair; (4) descend stairs; (5) drink glass; (8) get out of bed; (9) lie-down in bed; (10) pour water; (11) sit-down in chair; (12) stand-up from chair; (13) use telephone; and (14) walk. | T88: N/A | U88: R | V88: Unclear architecutre. They make user-dependent (a model using only the users data) and personal (general models that have been fine tuned) models. Personal model are called PM. They also use genral models (GM) | W88: Y (we don't know what model it is but they do different evaluations for PM, GM, and user-dependent) | X88: N/A | Y88: Y | Z88: "mean for each axis, standard deviation for each axis, maximum value of each axis, correlation between each pair of axes, mean of the magnitude, standard deviation of the magnitude, mean difference of the magnitude, and area under the curve of the magnitude" | AA88: 4 | AB88: N/A | AC88: 10-fold CV | AD88: Accuracy | AE88: Fig. 2 and 11 | AF88: N (they have for other datasets but not for WAO) | AG88: N | AH88: Y | AI88: N | AJ88: N | AL88: N | AM88: N | AN88: IP | AP88: N | AQ88: TTS | AS88: =IF(AND(AP88="N", ISBLANK(AQ88)), "THIS", "")
B89: 2 | C89: Classifier Personalization for Activity Recognition Using Wrist Accelerometers | D89: Andrea Mannini | E89: https://doi.org/10.1109/JBHI.2018.2869779 | F89: Jul. | G89: 2019 | H89: Mannini | I89: Y | K89: 90 | L89: 4 | M89: Wocket | N89: 33 | O89: "adults" | P89: Semi- or highly-supervised | Q89: N/A | R89: 4 | S89: Ambulation, Cycling, Other activities, Sedentary | T89: See Table 1 | U89: D | V89: SVM | W89: N | X89: LibSVM toolbox | Y89: Y | Z89: "Features were computed using SM data from each window, again following prior work [8]. Temporal and frequency features consisted of mean value, standard deviation, maximum value, range, first dominant frequency, ratio between the power at the dominant frequency and the total power, ratio between the power at frequencies higher than 3.5 Hz and the total power, and two signal fragmentation features (i.e., the number of high activity samples in the window, and the number of activations episodes in the window, see [8]). Signal fragmentation features that capture the level and duration of activity bursts within the window were also computed using the SM, as in previous work [8]." | AA89: 12.8 | AB89: 0 | AC89: LOSO CV | AD89: F1, Accuracy | AE89: Table 2 | AF89: N | AG89: N | AH89: Y (Youth and Adult in the same dataset) | AI89: N | AJ89: N | AL89: N | AM89: Y | AP89: Y | AS89: =IF(AND(AP89="N", ISBLANK(AQ89)), "THIS", "")
N90: 20 | O90: "youths" | P90: Semi- or highly-supervised | AS90: =IF(AND(AP90="N", ISBLANK(AQ90)), "THIS", "")
B91: 95 | C91: Smartwatch based activity recognition using active learning | D91: Farhad Shahmohammadi | E91: https://doi.org/10.1109/CHASE.2017.115 | F91: Jul | G91: 2017 | H91: SC | I91: N/A | K91: 10 | L91: N/A | M91: Samsung Gear Live | N91: 12 | O91: 8 M, 4 F, 22-28 yo | P91: Semi- or highly-supervised | Q91: N | R91: 5 | S91: running, walking, standing, sitting, and lying down. | T91: N/A | U91: N/A | V91: RF, ET, NB, LR, SVM | W91: Y | X91: N/A | Y91: Y | Z91: See Table 2 | AA91: 10 | AB91: N/A | AC91: LOSO CV | AD91: Accuracy, F1 | AE91: Fig. 4 and 5 | AF91: Y | AG91: Y | AH91: N | AI91: N | AJ91: N | AL91: N | AM91: N | AN91: IP | AP91: N | AQ91: DNA | AS91: =IF(AND(AP91="N", ISBLANK(AQ91)), "THIS", "")
B92: 110 | C92: From Lab to Real World: Assessing the Effectiveness of Human Activity Recognition and Optimization through Personalization | D92: Marija Stojchevska | E92: https://doi.org/10.3390/s23104606 | F92: May | G92: 2023 | H92: MHEALTH | I92: Y | K92: 32 | L92: N/A | M92: N/A | N92: 10 | O92: N/A | P92: Semi- or highly-supervised | Q92: Y | R92: 4 | S92: cycling, running, standing still, and walking | T92: N/A | U92: R | V92: CNN They asses the effect of training st size by using different cumulitive datasets (CDs) (CD 1 < CD 2 < … < CD 8) | W92: N | X92: N/A | Y92: N | AA92: 12 | AB92: 50 | AC92: LOSO CV | AD92: Balanced Accuracy, Logloss Macro and Micro F1 | AE92: Table 5, Fig. 11 and 12 | AF92: Y | AG92: N | AH92: Y | AI92: Y | AJ92: N | AL92: N | AM92: Y | AP92: Y | AS92: =IF(AND(AP92="N", ISBLANK(AQ92)), "THIS", "")
H93: SC | I93: Y | J93: https://cloud.ilabt.imec.be/index.php/s/2zkXxEDTTQgkN5y | K93: 32 | L93: 2 | M93: Empatica E4 | N93: 18 | O93: 5 F, 13 M, 22-45 yo | P93: Free-living | Q93: N | R93: 5 | S93: computer table, walking, running, cycling, standing still | T93: N/A | U93: N/A | AS93: =IF(AND(AP93="N", ISBLANK(AQ93)), "THIS", "")
B94: 67 | C94: A knowledge-light approach to personalised and open-ended human activity recognition | D94: Anjana Wijekoon | E94: https://doi.org/10.1016/j.knosys.2020.105651 | F94: Mar | G94: 2020 | H94: SC (SelfBack) | I94: Y | J94: https://archive.ics.uci.edu/dataset/521/selfback | K94: 100 | L94: N/A | M94: N/A | N94: 50 | O94: N/A | P94: Semi- or highly-supervised | Q94: N | R94: 9 | S94: walking downstairs, walking fast, walking moderate pace, walking slow, walking upstiars, standing, jogging, sitting, lying | T94: N/A | U94: R | V94: Matching Network | W94: N | X94: Keras | Y94: Y | Z94: See Sec. 5.2 | AA94: 5 | AB94: 0 | AC94: SS. 66/34 | AD94: Accuracy | AE94: Table 2 | AF94: N | AG94: Y | AH94: Y | AI94: N | AJ94: N | AL94: N | AM94: N | AN94: IF | AP94: N | AQ94: TTS | AS94: =IF(AND(AP94="N", ISBLANK(AQ94)), "THIS", "")
A95: Data Methodology (e.g., sensor location or device modality) | B95: 22 | C95: Smartwatch activity recognition feature comparison using ML.net | D95: Alexandru Alexan | E95: https://doi.org/10.1109/AQTR55203.2022.9801919 | F95: May | G95: 2022 | H95: WISDM | I95: Y | K95: 20 | L95: N/A | M95: LG W100 Smartwatch | N95: 51 | O95: N/A | P95: Semi- or highly-supervised | Q95: Y | R95: 18 | S95: Eating Soup (H), Eating Chips (I), Eating Pasta (J), Eating Sandwich (L), Drinking from Cup (K), Standing (E), Sitting (D), Walking (A), Jogging (B), Stairs (C), Typing (F), Brushing Teeth (G), Kicking (Soccer Ball) (M), Playing Catch w/Tennis Ball (O), Dribbling (Basketball) (P), Writing (Q), Clapping (R), Folding Clothes (S) | T95: N/A | U95: B | V95: FastForestOva, FastTreeOva, LbfgsLogisticRegressionOva, LbfgsMaximumEntropyMulti, LightGbmMulti, SdcaLogisticRegressionOva, SdcaMaximumEntropyMulti They evaluated 52 models in total because of different feature sets. | W95: Y | X95: ML.net | Y95: Y | Z95: "b) Binned distribution feature: contains 30 fields generated by using 10 bins for each axis. For each bin, the fraction of all values is used. c) Average feature: contains 3 fields, one for each axes, and represents the average sensor value for that chunk of data and axis. d) Time between peaks feature: contains 3 fields that indicate the time difference between the sinusoidal waves peaks. e) Average Absolute Difference feature: contains 3 fields for the average absolute difference of the chunk values and the mean value of these. f) Standard deviation feature: contains 3 fields indicating the standard deviation per axis. g) Variance feature: contains 3 fields indicating the variance per axis. h) MFCC feature: contains 39 fields indicating the Melfrequency cepstral coefficients. There are 13 fields per axis. i) Cosine distance feature: contains 3 fields indicating the cosine distances for the sensor values. j) Correlation feature: contains 3 fields indicating the correlations for the sensor values. k) Average resultant acceleration feature: contains 1 field indicating the average of the square root for the sum of squares for each axis value." | AA95: 10 | AB95: 0 | AC95: N/A | AD95: Accuracy | AE95: Table I, III, and IV | AF95: N | AG95: Y | AH95: N | AI95: N | AJ95: N | AL95: N | AM95: Y | AP95: N | AQ95: TTS | AS95: =IF(AND(AP95="N", ISBLANK(AQ95)), "THIS", "")
B96: 80 | C96: Estimating Energy Expenditure Using Body-Worn Accelerometers: A Comparison of Methods, Sensors Number and Positioning | D96: Marco Altini | E96: https://doi.org/10.1109/JBHI.2014.2313039 | F96: Mar | G96: 2014 | H96: SC | I96: N/A | K96: 64 | L96: N/A | M96: ADXL330 | N96: 15 | O96: 11 M, 4 F, mean age 29.8 (5.2) yo, mean weight 71.8 (15.9) kg, mean height 1.75 (0.10) cm, mean BMI 23.2 (3.0) kg/m2. | P96: Semi- or highly-supervised | Q96: N | R96: 2 | S96: sedentary (lying, sitting, standing) and active (whole body motions, walking, hiking, running) | T96: Lying (lying down resting), sitting (sitting resting, desk work, reading, writing, working on a PC, watching TV), and standing (standing resting, standing cooking) postures in our sedentary clusters. Active clusters were four, one representative of household activities, namely the high whole body motion (HWBM) cluster (stacking groceries, washing dishes, folding clothes, cleaning and scrubbing, washing windows, sweeping, vacuuming) and three representatives of locomotion and active transportation, such as walking, (self-paced, self-paced carrying books, treadmill flat: 3, 4, 5, 6 km/h, incline: 3, 5km/h, 5, 10%), biking (cycle ergometer, low, medium, and high resistance level at 60 and 80 r/min), and running (7, 8, 9, 10 km/h on a treadmill) | U96: D | V96: SVM (with kernel degree 5, lambda = 10, C = 1) | W96: N | X96: N/A | Y96: Y | Z96: "mean of the absolute BP signal, interquartile range, mean distance between axes, median, variance, standard deviation, zero crossing rate, main frequency peak, low and high-frequency band signal power" | AA96: 4 | AB96: N/A | AC96: LOSO CV | AD96: Accuracy | AE96: Fig. 5 | AF96: Y | AG96: Y | AH96: N | AI96: N | AJ96: N | AL96: N | AM96: N | AN96: IS | AP96: N | AQ96: DNA | AS96: =IF(AND(AP96="N", ISBLANK(AQ96)), "THIS", "")
B97: 10 | C97: Human Activity Recognition: A Comparative Study to Assess the Contribution Level of Accelerometer, ECG, and PPG Signals | D97: Mahsa Sadat Afzali Arani | E97: https://doi.org/10.3390/s21216997 | F97: Oct | G97: 2021 | H97: DaLiAc | I97: Y | K97: 32 | L97: N/A | M97: Empatica E4 | N97: 15 | O97: 21-55 yo, the data also includes "age, height, weight, fitness level, gender and skin type." | P97: Semi- or highly-supervised | Q97: N | R97: 5 (from 9) | S97: Sitting, ascending/descending stairs, playing table soccer, outdoor cycling, and walking | T97: Sitting: Sitting while reading Ascending/descending stairs: Climbing six floors up and going down, repeated two times Play table soccer: Playing table soccer, 1 vs. 1 Cycling: Cycling 2 km outdoors cycling with gravel and paved road condition Walking: Walking back from the canteen to the office, with some detour | U97: ND | V97: RF | W97: N | X97: trees = 300, 25 is max depth. Scikit learn | Y97: Y | Z97: See Table 2 and 3 | AA97: 7 | AB97: 0 | AC97: 10-fold CV (within subject classififciation) and LOSO CV | AD97: AUC, F1 | AE97: Fig. 5 and 7 | AF97: Y | AG97: Y | AH97: N | AI97: N | AJ97: N | AL97: N | AM97: Y | AP97: N | AQ97: TTS | AS97: =IF(AND(AP97="N", ISBLANK(AQ97)), "THIS", "")
B98: 96 | C98: Sensor Placement for Activity Detection Using Wearable Accelerometers | D98: Louis Atallah | E98: https://doi.org/10.1109/BSN.2010.23 | F98: Jun | G98: 2010 | H98: SC | I98: N/A | K98: 50 | L98: N/A | M98: N/A | N98: 11 | O98: 9 M, 2 F | P98: Semi- or highly-supervised | Q98: Y | R98: 5 | S98: very low level, low level, medium level, high level, transitional | T98: Table 2 | U98: R | V98: KNN, bayesian + gaussian | W98: Y | X98: N/A | Y98: Y | Z98: See Table III | AA98: 5 | AB98: 0 | AC98: LOSO CV | AD98: Precision, Recall | AE98: Fig. 4 | AF98: Y | AG98: Y | AH98: N | AI98: N | AJ98: N | AL98: N | AM98: Y | AP98: N | AQ98: DNA | AS98: =IF(AND(AP98="N", ISBLANK(AQ98)), "THIS", "")
B99: 120 | C99: Sensor positioning for activity recognition using wearable accelerometers | D99: Louis Atallah | E99: 10.1109/TBCAS.2011.2160540 | F99: Aug | G99: 2011 | H99: SC | K99: 50 | L99: 3 | M99: ADCL 330 | N99: 11 | O99: 9 M, 2 F | P99: Semi- or highly-supervised | Q99: N/A | R99: 15 | S99: See Table 2 | T99: See Table 2 | U99: N/A | V99: KNN | W99: N | X99: N/A | Y99: Y | Z99: See Table 3 | AA99: 5 | AB99: 0 | AC99: LOSO CV | AD99: Precision, Recall | AE99: Fig. 5 and 6 | AF99: N | AG99: Y | AH99: N | AI99: N | AJ99: N | AL99: N | AM99: Y | AP99: N | AQ99: DNA | AS99: =IF(AND(AP99="N", ISBLANK(AQ99)), "THIS", "")
B100: 148 | C100: WEAR: An Outdoor Sports Dataset for Wearable and Egocentric Activity Recognition | D100: Marius Bock | E100: 10.1145/3699776 | F100: Nov | G100: 2024 | H100: SC (WEAR) | I100: Y | J100: https://mariusbock.github.io/wear/ | K100: 50 | L100: 8 | M100: Bangle.js | N100: 22 | O100: 13 M / 9 F. "Mean age of 27.59 years (standard deviation (SD): 4.69), a mean height of 175.2 cm (SD: 9.83), and a mean weight of 69.74 kg (SD: 11.23)." | P100: Semi- or highly-supervised | Q100: Y. (90 s/activity) | R100: 18 (+ null) split into three "catagories" of activities | S100: jogging: normal, rotating arms, skipping, sidesteps, butt-kicks. Stretching: triceps, lunging, shoulders, hamstrings, lumbar rotation. Strength: push-ups, push-ups (complex), sit-ups, sit-ups (complex), burpees, lunges, lunges (complex), bench-dips | T100: N/A | U100: R | V100: ConvLSTM and TriDet | W100: Y | X100: N/A | Y100: N | AA100: 1 | AB100: 50 | AC100: LOSO CV | AD100: F1, mAP | AE100: Fig. 7 | AF100: N (they include classwise evaluations just not of wrist only) | AG100: Y | AH100: N | AI100: N | AJ100: Y | AK100: https://github.com/mariusbock/wear | AL100: N | AM100: Y | AP100: Y | AS100: =IF(AND(AP100="N", ISBLANK(AQ100)), "THIS", "")
...

Sheet Table_2
A1: Dataset (Raw Name) | B1: Count (by #) | D1: Dataset (Compiled) | E1: Count
A2: {=_xlfn.UNIQUE(All_Data!H3:'All_Data'!H180)} -> SC | B2: =COUNTIF(All_Data!H3:'All_Data'!H180, A2) -> 72 | D2: SC | E2: =B2+B12+B13+B23+B25+B34+B35+B38+B39+B40+B41 -> 82
A3: Bao + Intille | B3: =COUNTIF(All_Data!H4:'All_Data'!H181, A3) -> 1 | D3: Bao + Intille | E3: =B3+B20 -> 2
A4: HHAR | B4: =COUNTIF(All_Data!H5:'All_Data'!H182, A4) -> 7 | D4: HHAR | E4: =B4 -> 7
A5: PAMAP2 | B5: =COUNTIF(All_Data!H6:'All_Data'!H183, A5) -> 13 | D5: PAMAP2 | E5: =B5 -> 13
A6: RealWorld HAR | B6: =COUNTIF(All_Data!H7:'All_Data'!H184, A6) -> 5 | D6: RealWorld HAR | E6: =B34+B6 -> 6
A7: Extrasensory | B7: =COUNTIF(All_Data!H8:'All_Data'!H185, A7) -> 1 | D7: ExtraSensory | E7: =B7 -> 1
A8: WHARF | B8: =COUNTIF(All_Data!H9:'All_Data'!H186, A8) -> 6 | D8: WHARF | E8: =B8 -> 6
A9: MHEALTH | B9: =COUNTIF(All_Data!H10:'All_Data'!H187, A9) -> 6 | D9: WISDM | E9: =B10 -> 15
A10: WISDM | B10: =COUNTIF(All_Data!H11:'All_Data'!H188, A10) -> 15 | D10: CAPTURE-24 | E10: =B11 -> 1
A11: CAPTURE-24 | B11: =COUNTIF(All_Data!H12:'All_Data'!H189, A11) -> 1 | D11: Opportunity | E11: =B14 -> 4
A12: SC (Faculty of Sports) | B12: =COUNTIF(All_Data!H13:'All_Data'!H190, A12) -> 1 | D12: GENEActiv | E12: =B16 -> 1
A13: SC (JSI) | B13: =COUNTIF(All_Data!H14:'All_Data'!H191, A13) -> 1 | D13: Mannini | E13: =B17+B38 -> 4
A14: Opportunity | B14: =COUNTIF(All_Data!H15:'All_Data'!H192, A14) -> 4 | D14: SPHERE | E14: =B18 -> 2
A15: Aggregated 14 datasets | B15: =COUNTIF(All_Data!H16:'All_Data'!H193, A15) -> 1 | D15: UK BioBank | E15: =B19 -> 2
A16: GENEActiv | B16: =COUNTIF(All_Data!H17:'All_Data'!H194, A16) -> 1 | D16: DaLiAc | E16: =B21 -> 3
A17: Mannini | B17: =COUNTIF(All_Data!H18:'All_Data'!H195, A17) -> 3 | D17: ASTRI | E17: =B22 -> 1
A18: SPHERE | B18: =COUNTIF(All_Data!H19:'All_Data'!H196, A18) -> 2 | D18: Cleland | E18: =B24 -> 2
A19: UK BioBank | B19: =COUNTIF(All_Data!H20:'All_Data'!H197, A19) -> 2 | D19: DHA | E19: =B26 -> 3
A20: MIT (not cited) Bao + Intille | B20: =COUNTIF(All_Data!H21:'All_Data'!H198, A20) -> 1 | D20: IMSBD | E20: =B27 -> 1
A21: DaLiAc | B21: =COUNTIF(All_Data!H22:'All_Data'!H199, A21) -> 3 | D21: TwistAR | E21: =B28 -> 1
A22: ASTRI | B22: =COUNTIF(All_Data!H23:'All_Data'!H200, A22) -> 1 | D22: HMP | E22: =B29 -> 1
A23: SC (WSMC-HAR) | B23: =COUNTIF(All_Data!H24:'All_Data'!H201, A23) -> 2 | D23: GOTOv | E23: =B30 -> 1
A24: Cleland | B24: =COUNTIF(All_Data!H25:'All_Data'!H202, A24) -> 2 | D24: harAGE | E24: =B31 -> 1
A25: SC (ChoresXL) | B25: =COUNTIF(All_Data!H26:'All_Data'!H203, A25) -> 1 | D25: SHL | E25: =B32 -> 1
A26: DHA | B26: =COUNTIF(All_Data!H27:'All_Data'!H204, A26) -> 3 | D26: IMEC | E26: =B41 -> 1
A27: IM-Sporting Behaviors Dataset | B27: =COUNTIF(All_Data!H28:'All_Data'!H205, A27) -> 1 | D27: Oulu | E27: =B42 -> 1
A28: TWristAR | B28: =COUNTIF(All_Data!H29:'All_Data'!H206, A28) -> 1 | D28: DSADS | E28: =B43 -> 3
A29: HMP | B29: =COUNTIF(All_Data!H30:'All_Data'!H207, A29) -> 1 | D29: MHEALTH | E29: =B9 -> 6
A30: GOTOv | B30: =COUNTIF(All_Data!H31:'All_Data'!H208, A30) -> 1
A31: harAGE | B31: =COUNTIF(All_Data!H32:'All_Data'!H209, A31) -> 1
A32: SHL (Preview) | B32: =COUNTIF(All_Data!H33:'All_Data'!H210, A32) -> 1
A33: SC (DAAD) | B33: =COUNTIF(All_Data!H34:'All_Data'!H211, A33) -> 1
A34: SC (Realworld HAR) | B34: =COUNTIF(All_Data!H35:'All_Data'!H212, A34) -> 1
A35: 0 | B35: =COUNTIF(All_Data!H36:'All_Data'!H213, A35) -> 0
A36: SC (SelfBack) | B36: =COUNTIF(All_Data!H37:'All_Data'!H214, A36) -> 1
A37: SC (WEAR) | B37: =COUNTIF(All_Data!H38:'All_Data'!H215, A37) -> 1
A38: SC (Mannini) | B38: =COUNTIF(All_Data!H39:'All_Data'!H216, A38) -> 1
A39: SC (PAAWS) | B39: =COUNTIF(All_Data!H40:'All_Data'!H217, A39) -> 1
A40: SC? (Seems to be WISDM, not credited) | B40: =COUNTIF(All_Data!H41:'All_Data'!H218, A40) -> 1
A41: IMEC | B41: =COUNTIF(All_Data!H42:'All_Data'!H219, A41) -> 1
A42: Oulu | B42: =COUNTIF(All_Data!H43:'All_Data'!H220, A42) -> 1
A43: DSADS | B43: =COUNTIF(All_Data!H44:'All_Data'!H221, A43) -> 3
A44: Unnamed Daily activities | B44: =COUNTIF(All_Data!H45:'All_Data'!H222, A44) -> 1

Sheet Table_3
A1: Contribution Area | B1: Article ID | C1: Title | D1: First Author | E1: Reproducible | F1: Replicable | G1: Weights | H1: Algorithms | I1: Data | J1: Cross DS | K1: Mult DS | L1: Classwise | M1: Baseline | N1: Single Split | O1: k-fold CV | P1: LOSO CV | Q1: R | R1: ND | S1: L | T1: D | U1: B | V1: 10+ | W1: 9 6 to 9 | X1: 2 to 5
A2: Algorithmic Changes (e.g., architecture or preprocessing) | B2: 66 | C2: A Hybrid Solution for Human Activity Recognition: Application to Wrist-Worn Accelerometry | D2: Manuel Abbas | L2: \gcheck | M2: \gcheck | O2: \gcheck | X2: \gcheck
B3: 94 | C3: Characterizing Peaks in Acceleration Signals–Application to Physical Activity Detection Using Wearable Sensors | D3: Manuel Abbas | F3: \gcheck | L3: \gcheck | M3: \gcheck | O3: \gcheck | P3: \gcheck | X3: \gcheck
B4: 5 | C4: Daily living activity recognition based on statistical feature quality group selection | D4: Oresti Banos | I4: \gcheck | K4: \ycheck | M4: \gcheck | O4: \gcheck | X4: \gcheck
B5: 24 | C5: Significant Features for Human Activity Recognition Using Tri-Axial Accelerometers | D5: Mohamed Bennasar | I5: \gcheck | K5: \gcheck | M5: \gcheck | O5: \gcheck | T5: \gcheck | V5: \gcheck | W5: \gcheck
B6: 25 | C6: Improving Deep Learning for HAR with Shallow LSTMs | D6: Marius Bock | E6: \gcheck | F6: \gcheck | G6: \ycheck | H6: \gcheck | I6: \gcheck | K6: \gcheck | M6: \gcheck | P6: \gcheck | W6: \gcheck
B7: 151 | C7: Handling heterogeneity in Human Activity Recognition data by a compact Long Short Term Memory based deep learning approach | D7: Ahmed Cemiloglu | I7: \gcheck | L7: \gcheck | M7: \gcheck | N7: \gcheck | U7: \gcheck | W7: \gcheck
B8: 59 | C8: Activity classification using a single wrist-worn accelerometer | D8: Saisakul Chernbumroong | M8: \gcheck | O8: \gcheck | R8: \gcheck | X8: \gcheck
B9: 39 | C9: Temporal Alignment Improves Feature Quality: An Experiment on Activity Recognition with Accelerometer Data | D9: Hongjun Choi | L9: \gcheck | P9: \gcheck | R9: \gcheck | W9: \gcheck
B10: 132 | C10: Ensemble Methods for Classification of Physical Activities from Wrist Accelerometry | D10: Aok Kumar Chowdhury | E10: \gcheck | F10: \gcheck | H10: \gcheck | I10: \gcheck | K10: \gcheck | L10: \gcheck | M10: \gcheck | P10: \gcheck | R10: \gcheck | T10: \gcheck | W10: \gcheck | X10: \gcheck
B11: 155 | C11: Situation identification in smart wearable computing systems based on machine learning and Context Space Theory | D11: Giuseppe D'Aniello | E11: \gcheck | F11: \gcheck | H11: \gcheck | I11: \gcheck | L11: \ycheck | M11: \gcheck | O11: \gcheck | X11: \gcheck
B12: 83 | C12: Comparing Supervised Learning Techniques on the Task of Physical Activity Recognition | D12: Anthony Dalton | F12: \gcheck | M12: \gcheck | P12: \gcheck | T12: \gcheck | V12: \gcheck
B13: 99 | C13: Recognition of Human Behavior for Assisted Living Using Dictionary Learning Approach | D13: Pubali De | I13: \gcheck | L13: \gcheck | M13: \gcheck | N13: \gcheck | W13: \gcheck
B14: 46 | C14: Multi-Criteria Analysis of Sensor Reliability for Wearable Human Activity Recognition | D14: Yilin Dong | I14: \gcheck | L14: \gcheck | M14: \gcheck | O14: \gcheck | Q14: \gcheck | V14: \gcheck
B15: 87 | C15: Temporal-channel convolution with self-attention network for human activity recognition using wearable sensors | D15: Ehab Essa | I15: \gcheck | K15: \gcheck | L15: \gcheck | M15: \gcheck | P15: \gcheck | Q15: \gcheck | V15: \gcheck
B16: 13 | C16: Matched Filter Interpretation of CNN Classifiers with Application to HAR | D16: Mohammed M. Farag | F16: \gcheck | I16: \gcheck | K16: \gcheck | L16: \gcheck | N16: \gcheck | W16: \gcheck
B17: 14 | C17: AccNet24: A deep learning framework for classifying 24-hour activity behaviours from wrist-worn accelerometer data under free-living environments | D17: Vahid Farrahi | I17: \gcheck | L17: \gcheck | M17: \gcheck | N17: \gcheck | X17: \gcheck
B18: 85 | C18: A Comparative Study on Fitness Activity Recognition | D18: Igor Lopes de Faria | M18: \gcheck | O18: \gcheck | X18: \gcheck
B19: 7 | C19: Improving Activity Recognition while Reducing Misclassification of Unknown Activities | D19: Andrea Fasciglione | N19: \gcheck | T19: \gcheck | V19: \gcheck
B20: 152 | C20: Modelling time-series data generation with diffusion models for triaxial data | D20: Francisco M. Garcia-Moreno | E20: \gcheck | F20: \gcheck | H20: \gcheck | I20: \gcheck | M20: \gcheck | P20: \gcheck | X20: \gcheck
B21: 15 | C21: How Accurately Can Your Wrist Device Recognize Daily Activities and Detect Falls? | D21: Martin Gjoreski | I21: \ycheck | K21: \gcheck | L21: \gcheck | M21: \gcheck | P21: \gcheck | Q21: \gcheck | U21: \gcheck | V21: \gcheck | X21: \gcheck
B22: 31 | C22: Reducing the Impact of Sensor Orientation Variability in Human Activity Recognition Using a Consistent Reference System | D22: Manuel Gil-Martín | F22: \gcheck | I22: \gcheck | K22: \gcheck | O22: \gcheck | P22: \gcheck | T22: \gcheck | V22: \gcheck
B23: 88 | C23: Towards Learning Discrete Representations via Self-Supervision for Wearables-Based Human Activity Recognition | D23: Harish Haresamudram | E23: \gcheck | F23: \gcheck | I23: \gcheck | K23: \gcheck | M23: \gcheck | O23: \gcheck | W23: \gcheck
B24: 76 | C24: Deep Learning Approach for Complex Activity Recognition using Heterogeneous Sensors from Wearable Device | D24: Narit Hnoohom | F24: \gcheck | I24: \gcheck | M24: \gcheck | O24: \gcheck | V24: \gcheck
B25: 61 | C25: Activity Recognition with Wristband Based on Histogram and Bayesian Classifiers | D25: Yi-Cong Huang | L25: \gcheck | X25: \gcheck
B26: 37 | C26: A Comprehensive Analysis on Wearable Acceleration Sensors in Human Activity Recognition | D26: Majid Janidarmian | E26: \gcheck | F26: \gcheck | I26: \gcheck | M26: \gcheck | P26: \gcheck | U26: \gcheck | W26: \gcheck
B27: 79 | C27: Topological persistence guided knowledge distillation for wearable sensor data | D27: Eun Som Jeon | H27: \ycheck | I27: \gcheck | K27: \gcheck | L27: \gcheck | N27: \gcheck | V27: \gcheck
B28: 105 | C28: Deep Neural Networks for Time Series Classification in Human Activity Recognition | D28: Shreehar Joshi | F28: \gcheck | I28: \gcheck | L28: \gcheck | M28: \gcheck | N28: \gcheck | V28: \gcheck
B29: 43 | C29: Rich learning representations for human activity recognition: How to empower deep feature learning for biological time series | D29: Ria Kanjilal | I29: \gcheck | M29: \gcheck | P29: \gcheck | X29: \gcheck
B30: 58 | C30: A general framework for sensor-based human activity recognition | D30: Lukas Köping | F30: \gcheck | H30: \ycheck | L30: \gcheck | V30: \gcheck
B31: 62 | C31: A Deep Learning-Based Semantic Segmentation Model Using MCNN and Attention Layer for Human Activity Recognition | D31: Sang-hyub Lee | F31: \gcheck | L31: \gcheck | M31: \gcheck | P31: \gcheck | Q31: \gcheck | V31: \gcheck
B32: 115 | C32: Accelerometer Dense Trajectories for Activity Recognition and People Identification | D32: Roberto Leyva | I32: \gcheck | K32: \gcheck | P32: \gcheck | V32: \gcheck
B33: 112 | C33: Human activity recognition based on triaxial accelerometer using multi-feature weighted ensemble | D33: QingNan Li | L33: \gcheck | M33: \gcheck | N33: \gcheck | W33: \gcheck
B34: 103 | C34: Human Activity Recognition in Free Living Using a Wearable Sensor: A Two-Stage Approach | D34: Tianhui Li | K34: \gcheck | N34: \gcheck | R34: \gcheck | X34: \gcheck
B35: 142 | C35: Frequency-Aware Masked Autoencoders for Human Activity Recognition using Accelerometers | D35: Niels R. Lorenzen | F35: \gcheck | I35: \gcheck | L35: \gcheck | N35: \gcheck | W35: \gcheck
B36: 98 | C36: Research on human activity recognition based on active learning | D36: Rong Liu | I36: \gcheck | N36: \gcheck | T36: \gcheck | V36: \gcheck
B37: 102 | C37: MFE-HAR: multiscale feature engineering for human activity recognitionusing wearable sensors | D37: Jianchao Lu | I37: \gcheck | K37: \gcheck | L37: \gcheck | M37: \gcheck | Q37: \gcheck | V37: \gcheck
B38: 51 | C38: Robust Single Accelerometer-Based Activity Recognition Using Modified Recurrence Plot | D38: Jianjie Lu | E38: \gcheck | F38: \gcheck | G38: \gcheck | H38: \gcheck | I38: \gcheck | K38: \gcheck | L38: \gcheck | M38: \gcheck | N38: \gcheck | W38: \gcheck | X38: \gcheck
B39: 150 | C39: A two-stage multi-branch fusion model for human activity recognition based on sensor data transformed by gramian angular difference field | D39: Limeng Lu | F39: \gcheck | I39: \gcheck | K39: \gcheck | L39: \gcheck | M39: \ycheck | X39: \gcheck
B40: 97 | C40: Wearable Computing for Internet of Things: A Discriminant Approach for Human Activity Recognition | D40: Wei Lu | I40: \gcheck | K40: \gcheck | M40: \gcheck | N40: \gcheck | Q40: \gcheck | V40: \gcheck
B41: 130 | C41: Data augmentation for Human Activity Recognition with Generative Adversarial Networks | D41: Marcos Lupion | F41: \gcheck | H41: \gcheck | I41: \gcheck | M41: \gcheck | N41: \gcheck | T41: \gcheck | V41: \gcheck
B42: 41 | C42: Smart-Wearable Sensors and CNN-BiGRU Model: A Powerful Combination for Human Activity Recognition | D42: Hazma Ali Imran | F42: \gcheck | I42: \gcheck | K42: \gcheck | L42: \gcheck | M42: \gcheck | O42: \gcheck | T42: \gcheck | V42: \gcheck
B43: 63 | C43: Age Differences in Estimating Physical Activity by Wrist Accelerometry Using Machine Learning | D43: Mamoun T. Mardini | L43: \gcheck | M43: \gcheck | O43: \gcheck | Q43: \gcheck | V43: \gcheck
B44: 78 | C44: User-Independent Recognition of Sports Activities From a Single Wrist-Worn Accelerometer: A Template-Matching-Based Approach | D44: Jenny Margarito | L44: \gcheck | M44: \gcheck | N44: \gcheck | W44: \gcheck
B45: 47 | C45: An Activity Recognition Framework Deploying the Random Forest Classifier and A Single Optical Heart Rate Monitoring and Triaxial Accelerometer Wrist-Band | D45: Saeed Mehrang | F45: \gcheck | L45: \gcheck | P45: \gcheck | T45: \gcheck | X45: \gcheck
B46: 54 | C46: Sensor-based Complex Human Activity Recognition from Smartwatch Data using Hybrid Deep Learning Network | D46: Sakorn Mekruksavanich | I46: \gcheck | M46: \gcheck | O46: \gcheck | T46: \gcheck | V46: \gcheck
B47: 124 | C47: RNN-based deep learning for physical activity recognition using smartwatch sensors: A case study of simple and complex activity recognition | D47: Sakron Mekruksavanich | E47: \gcheck | F47: \gcheck | I47: \gcheck | K47: \gcheck | M47: \gcheck | P47: \gcheck | T47: \gcheck | V47: \gcheck
B48: 77 | C48: Recognizing and Understanding Sport Activities Based on Wearable Sensor Signals Using Deep Residual Network | D48: Sakorn Mekruksavanich | I48: \gcheck | M48: \gcheck | O48: \gcheck | T48: \gcheck | W48: \gcheck
B49: 107 | C49: Efficient Recognition of Complex Human Activities Based on Smartwatch Sensors Using Deep Pyramidal Residual Network | D49: Sakorn Mekruksavanich | I49: \gcheck | L49: \gcheck | M49: \gcheck | T49: \gcheck | V49: \gcheck
B50: 104 | C50: Deep Learning Networks for Complex Activity Recognition Based on Wrist-Worn Sensor | D50: Sakorn Mekruksavanich | I50: \gcheck | L50: \gcheck | M50: \gcheck | O50: \gcheck | Q50: \gcheck | V50: \gcheck
B51: 139 | C51: Effect of Sliding Window Sizes on Sensor-Based Human Activity Recognition Using Smartwatch Sensors and Deep Learning Approaches | D51: Sakorn Mekruksavanich | I51: \gcheck | M51: \gcheck | V51: \gcheck
B52: 143 | C52: A Deep Hybrid Neural Network for Efficient Human Activity Recognition Based on Accelerometer Data from Wristband | D52: Sakorn Mekruksavanich | I52: \gcheck | L52: \gcheck | M52: \gcheck | O52: \gcheck | Q52: \gcheck | W52: \gcheck
B53: 108 | C53: Evaluating the Impact of a Two-Stage Multivariate Data Cleansing Approach to Improve to the Performance of Machine Learning Classifiers: A Case Study in Human Activity Recognition | D53: Dionicio Neira-Rodado | I53: \gcheck | M53: \gcheck | O53: \gcheck | T53: \gcheck | V53: \gcheck
B54: 106 | C54: Design and assessment of the data analysis process for a wrist-worn smart object to detect atomic activities in the smart home | D54: Qin Ni | L54: \gcheck | M54: \gcheck | O54: \gcheck | S54: \gcheck | V54: \gcheck
B55: 149 | C55: Language of actions: A generative model for activity recognition and next move prediction from motion sensors | D55: Hasan Ogul | I55: \gcheck | K55: \gcheck | L55: \ycheck | M55: \ycheck | O55: \gcheck | Q55: \gcheck | W55: \gcheck
B56: 35 | C56: Building robust models for Human Activity Recognition from raw accelerometers data using Gated Recurrent Units and Long Short Term Memory Neural Networks | D56: Jeremiah Okai | I56: \gcheck | L56: \gcheck | M56: \gcheck | P56: \gcheck | V56: \gcheck
B57: 70 | C57: An Approach towards Position-Independent Human Activity Recognition Model based on Wearable Accelerometer Sensor | D57: Naima Qamar | I57: \gcheck | L57: \gcheck | M57: \gcheck | O57: \gcheck | V57: \gcheck
B58: 57 | C58: A Transformer Based Approach for Activity Detection | D58: Gulshan Sharma | I58: \gcheck | L58: \gcheck | M58: \gcheck | W58: \gcheck
B59: 68 | C59: An adaptive time window method for human activity recognition | D59: Zhang Sheng | F59: \gcheck | L59: \gcheck | O59: \gcheck | W59: \gcheck
B60: 121 | C60: Mobile sensor based human activity recognition: distinguishing of challenging activities by applying long short-term memory deep learning modified by residual network concept | D60: Seyed Vahab Shojaedini | F60: \gcheck | I60: \gcheck | K60: \gcheck | L60: \gcheck | M60: \gcheck | W60: \gcheck
B61: 140 | C61: Transportation Mode Recognition Based on Low-Rate Acceleration and Location Signals With an Attention-Based Multiple-Instance Learning Network | D61: Christos Siargkas | I61: \gcheck | L61: \ycheck | M61: \gcheck | P61: \gcheck | W61: \gcheck
B62: 114 | C62: Improving the classification accuracy of streaming data using SAX similarity features | D62: Pekka Siirtola | F62: \gcheck | K62: \gcheck | M62: \gcheck | S62: \gcheck | X62: \gcheck
B63: 93 | C63: Smart Devices are Different: Assessing and Mitigating Mobile Sensing Heterogeneities for Activity Recognition | D63: Allan Stisen | I63: \gcheck | M63: \gcheck | O63: \gcheck | P63: \gcheck | U63: \gcheck | W63: \gcheck
B64: 136 | C64: Ngram time series model to predict activity type and energy cost from wrist, hip and ankle accelerometers: implications of age | D64: Scott J Strath | L64: \gcheck | P64: \gcheck | R64: \gcheck | W64: \gcheck
B65: 74 | C65: CapsGaNet: Deep Neural Network Based on Capsule and GRU for Human Activity Recognition | D65: Xiaojie Sun | K65: \gcheck | L65: \gcheck | M65: \gcheck | N65: \gcheck | Q65: \gcheck | W65: \gcheck
B66: 49 | C66: On-body localization of wearable devices: An investigation of position-aware activity recognition | D66: Timo Sztyler | H66: \ycheck | I66: \gcheck | L66: \gcheck | O66: \gcheck | S66: \gcheck | W66: \gcheck
B67: 100 | C67: Position-aware activity recognition with wearable devices | D67: Timo Sztyler | H67: \ycheck | I67: \gcheck | L67: \gcheck | N67: \gcheck | O67: \gcheck | P67: \gcheck | W67: \gcheck
B68: 141 | C68: Quantum-based Gated Recurrent Units for Multiclass Classification to Monitor Daily Living Activities for Early Disease Detection | D68: Bao-Nhi Dang Tran | I68: \gcheck | L68: \gcheck | N68: \gcheck | Q68: \gcheck | W68: \gcheck
B69: 18 | C69: An Improved Activity Recognition Method Based on Smart Watch Data | D69: Dengpan Tian | L69: \gcheck | X69: \gcheck
B70: 48 | C70: Selective Ensemble Based on Extreme Learning Machine for Sensor-Based Human Activity Recognition | D70: Yiming Tian | F70: \gcheck | L70: \gcheck | M70: \gcheck | P70: \gcheck | S70: \gcheck | W70: \gcheck
B71: 72 | C71: A Novel Sensor-Based Human Activity Recognition Method Based on Hybrid Feature Selection and Combinational Optimization | D71: Yiming Tian | F71: \gcheck | L71: \gcheck | M71: \gcheck | P71: \gcheck | S71: \gcheck | W71: \gcheck
B72: 92 | C72: Human activity recognition based on random forests | D72: Lu Xu | F72: \gcheck | L72: \gcheck | M72: \gcheck | N72: \gcheck | W72: \gcheck
B73: 60 | C73: Activity Recognition Using One-Versus-All Strategy with Relief-F and Self-Adaptive Algorithm | D73: M. N Shah Zainudin | I73: \gcheck | L73: \gcheck | N73: \gcheck | T73: \gcheck | V73: \gcheck
B74: 145 | C74: An enhanced dual inception-attention-BiGRU-attention model integrating wavelet transform for wearable sensor-based human activity recognition | D74: Xingao Zhang | E74: \gcheck | F74: \gcheck | H74: \gcheck | I74: \gcheck | K74: \gcheck | L74: \gcheck | M74: \gcheck | N74: \gcheck | X74: \gcheck
B75: 45 | C75: Human Activity Recognition Based on Motion Sensor Using U-Net | D75: Yong Zhang | F75: \gcheck | H75: \gcheck | I75: \gcheck | K75: \gcheck | L75: \gcheck | M75: \gcheck | N75: \gcheck | W75: \gcheck
B76: 29 | C76: Comparison of Data Preprocessing Approaches for Applying Deep Learning to Human Activity Recognition in the Context of Industry 4.0 | D76: Xiaochen Zheng | F76: \gcheck | H76: \gcheck | I76: \gcheck | L76: \ycheck | N76: \gcheck | W76: \gcheck
B77: 113 | C77: A Human Activity Recognition Model Based on Wearable Sensor | D77: Fan Zhou | L77: \gcheck | M77: \gcheck | W77: \gcheck
B78: Cat. total | C78: =COUNT(B2:B77) -> 76 | D78: Count | E78: =COUNTIF(E2:E77, "\gcheck") -> 9 | F78: =COUNTIF(F2:F77, "\gcheck") -> 30 | G78: =COUNTIF(G2:G77, "\gcheck") -> 1 | H78: =COUNTIF(H2:H77, "\gcheck") -> 9 | I78: =COUNTIF(I2:I77, "\gcheck") -> 50 | J78: =COUNTIF(J2:J77, "\gcheck") -> 0 | K78: =COUNTIF(K2:K77, "\gcheck") -> 23 | L78: =COUNTIF(L2:L77, "\gcheck") -> 47 | ... X78: =COUNTIF(X2:X77, "\gcheck") -> 19
D79: Percentage | E79: =ROUND(E78/$C$78*100, 2) -> 11.84 | F79: =ROUND(F78/$C$78*100, 2) -> 39.47 | G79: =ROUND(G78/$C$78*100, 2) -> 1.32 | H79: =ROUND(H78/$C$78*100, 2) -> 11.84 | I79: =ROUND(I78/$C$78*100, 2) -> 65.79 | J79: =ROUND(J78/$C$78*100, 2) -> 0 | K79: =ROUND(K78/$C$78*100, 2) -> 30.26 | L79: =ROUND(L78/$C$78*100, 2) -> 61.84 | ... X79: =ROUND(X78/$C$78*100, 2) -> 25
A80: Personalized HAR | B80: 26 | C80: Personalized Activity Recognition with Deep Triplet Embeddings | D80: David Burns | F80: \gcheck | H80: \gcheck | I80: \gcheck | M80: \gcheck | O80: \gcheck | V80: \gcheck
B81: 122 | C81: Activity Recognition Using Community Data to Complement Small Amounts of Labeled Instances | D81: Enrique Garcia-Ceja | I81: \gcheck | K81: \gcheck | L81: \ycheck | M81: \gcheck | O81: \gcheck | Q81: \gcheck | V81: \gcheck
B82: 2 | C82: Classifier Personalization for Activity Recognition Using Wrist Accelerometers | D82: Andrea Mannini | E82: \gcheck | F82: \gcheck | I82: \gcheck | K82: \ycheck | P82: \gcheck | T82: \gcheck | X82: \gcheck
B83: 95 | C83: Smartwatch based activity recognition using active learning | D83: Farhad Shahmohammadi | L83: \gcheck | M83: \gcheck | P83: \gcheck | X83: \gcheck
B84: 110 | C84: From Lab to Real World: Assessing the Effectiveness of Human Activity Recognition and Optimization through Personalization | D84: Marija Stojchevska | E84: \gcheck | F84: \gcheck | I84: \gcheck | J84: \gcheck | K84: \gcheck | L84: \gcheck | P84: \gcheck | Q84: \gcheck | X84: \gcheck
B85: 67 | C85: A knowledge-light approach to personalised and open-ended human activity recognition | D85: Anjana Wijekoon | I85: \gcheck | K85: \gcheck | N85: \gcheck | Q85: \gcheck | W85: \gcheck
B86: Cat. total | C86: =COUNT(B80:B85) -> 6 | D86: Count | E86: =COUNTIF(E80:E85, "\gcheck") -> 2 | F86: =COUNTIF(F80:F85, "\gcheck") -> 3 | G86: =COUNTIF(G80:G85, "\gcheck") -> 0 | H86: =COUNTIF(H80:H85, "\gcheck") -> 1 | I86: =COUNTIF(I80:I85, "\gcheck") -> 5 | J86: =COUNTIF(J80:J85, "\gcheck") -> 1 | K86: =COUNTIF(K80:K85, "\gcheck") -> 3 | L86: =COUNTIF(L80:L85, "\gcheck") -> 2 | ... X86: =COUNTIF(X80:X85, "\gcheck") -> 3
D87: Percentage | E87: =ROUND(E86/$C$86*100,2) -> 33.33 | F87: =ROUND(F86/$C$86*100,2) -> 50 | G87: =ROUND(G86/$C$86*100,2) -> 0 | H87: =ROUND(H86/$C$86*100,2) -> 16.67 | I87: =ROUND(I86/$C$86*100,2) -> 83.33 | J87: =ROUND(J86/$C$86*100,2) -> 16.67 | K87: =ROUND(K86/$C$86*100,2) -> 50 | L87: =ROUND(L86/$C$86*100,2) -> 33.33 | ... X87: =ROUND(X86/$C$86*100,2) -> 50
A88: Data Methodology (e.g., sensor location or device modality) | B88: 22 | C88: Smartwatch activity recognition feature comparison using ML.net | D88: Alexandru Alexan | F88: \gcheck | I88: \gcheck | M88: \gcheck | U88: \gcheck | V88: \gcheck
B89: 80 | C89: Estimating Energy Expenditure Using Body-Worn Accelerometers: A Comparison of Methods, Sensors Number and Positioning | D89: Marco Altini | L89: \gcheck | P89: \gcheck | T89: \gcheck | X89: \gcheck
B90: 10 | C90: Human Activity Recognition: A Comparative Study to Assess the Contribution Level of Accelerometer, ECG, and PPG Signals | D90: Mahsa Sadat Afzali Arani | F90: \gcheck | I90: \gcheck | L90: \gcheck | O90: \gcheck | P90: \gcheck | R90: \gcheck | X90: \gcheck
B91: 96 | C91: Sensor Placement for Activity Detection Using Wearable Accelerometers | D91: Louis Atallah | F91: \gcheck | L91: \gcheck | M91: \gcheck | P91: \gcheck | Q91: \gcheck | X91: \gcheck
B92: 120 | C92: Sensor positioning for activity recognition using wearable accelerometers | D92: Louis Atallah | F92: \gcheck | P92: \gcheck | V92: \gcheck
B93: 148 | C93: WEAR: An Outdoor Sports Dataset for Wearable and Egocentric Activity Recognition | D93: Marius Bock | E93: \gcheck | F93: \gcheck | H93: \gcheck | I93: \gcheck | L93: \ycheck | M93: \gcheck | P93: \gcheck | Q93: \gcheck | V93: \gcheck
B94: 17 | C94: Optimal Placement of Accelerometers for the Detection of Everyday Activities | D94: Ian Cleland | L94: \gcheck | M94: \gcheck | O94: \gcheck | S94: \gcheck | W94: \gcheck
B95: 154 | C95: Assessing the impact of body location on the accuracy of detecting daily activities with accelerometer data | D95: Xiangnan Dang | E95: \gcheck | F95: \gcheck | H95: \gcheck | I95: \gcheck | K95: \gcheck | L95: \gcheck | M95: \gcheck | O95: \gcheck | U95: \gcheck | V95: \gcheck
B96: 116 | C96: The Effect of Sensor Placement and Number on Physical Activity Recognition and Energy Expenditure Estimation in Older Adults: Validation Study | D96: Anis Davoudi | L96: \gcheck | O96: \gcheck | Q96: \gcheck | V96: \gcheck
B97: 109 | C97: Free-living Ambulatory Activity Classification: A Comparative Analysis of Wrist-worn, Insole-embedded, and Phone-embedded Sensors | D97: Ton T. H. Duong | F97: \gcheck | L97: \gcheck | P97: \gcheck | T97: \gcheck | X97: \gcheck
B98: 34 | C98: Evaluating sensor placement and modality for activity recognition inactive games | D98: Natalie Jablonsky | O98: \gcheck | T98: \gcheck | X98: \gcheck
B99: 69 | C99: Analyzing Body Movements within the Laban Effort Framework Using a Single Accelerometer | D99: Basel Kikhia | F99: \gcheck | L99: \gcheck | M99: \gcheck | P99: \gcheck | T99: \gcheck | W99: \gcheck
B100: 137 | C100: Activity recognition using a single accelerometer placed at the wrist or ankle | D100: Andrea Mannini | E100: \gcheck | F100: \gcheck | H100: \gcheck | I100: \gcheck | L100: \gcheck | P100: \gcheck | T100: \gcheck | X100: \gcheck
...

Sheet Fig_3
A1: Meta Data | E1: Missing Atrribute
A2: Contribution Area | B2: Article ID | C2: Title | D2: First Author | E2: Device | F2: Frequency | G2: Range | H2: Definitions | I2: Wrist | J2: Demographics | K2: n | L2: Length | M2: Overlap | N2: Data | O2: Libraries | P2: TTS
A3: Algorithm Improvement (e.g., architecture or preprocessing) | B3: 66 | C3: A Hybrid Solution for Human Activity Recognition: Application to Wrist-Worn Accelerometry | D3: Manuel Abbas | I3: N | N3: N | O3: N
B4: 94 | C4: Characterizing Peaks in Acceleration Signals–Application to Physical Activity Detection Using Wearable Sensors | D4: Manuel Abbas | I4: N | N4: N | O4: N
B5: 5 | C5: Daily living activity recognition based on statistical feature quality group selection | D5: Oresti Banos | E5: N | G5: N | H5: N | I5: N | J5: N | K5: N | L5: N | M5: N | O5: N
B6: 24 | C6: Significant Features for Human Activity Recognition Using Tri-Axial Accelerometers | D6: Mohamed Bennasar | E6: N | G6: N | H6: N | I6: N | M6: N
B7: 25 | C7: Improving Deep Learning for HAR with Shallow LSTMs | D7: Marius Bock | E7: N | G7: N | H7: N | I7: N | J7: N
B8: 151 | C8: Handling heterogeneity in Human Activity Recognition data by a compact Long Short Term Memory based deep learning approach | D8: Ahmed Cemiloglu | G8: N | H8: N | M8: N
B9: 59 | C9: Activity classification using a single wrist-worn accelerometer | D9: Saisakul Chernbumroong | N9: N
B10: 39 | C10: Temporal Alignment Improves Feature Quality: An Experiment on Activity Recognition with Accelerometer Data | D10: Hongjun Choi | F10: N | G10: N | H10: N | M10: N | N10: N
B11: 132 | C11: Ensemble Methods for Classification of Physical Activities from Wrist Accelerometry | D11: Aok Kumar Chowdhury | H11: N
B12: 155 | C12: Situation identification in smart wearable computing systems based on machine learning and Context Space Theory | D12: Giuseppe D'Aniello | E12: N | G12: N | I12: N | J12: N
B13: 83 | C13: Comparing Supervised Learning Techniques on the Task of Physical Activity Recognition | D13: Anthony Dalton | E13: N | N13: N
B14: 99 | C14: Recognition of Human Behavior for Assisted Living Using Dictionary Learning Approach | D14: Pubali De | E14: N | H14: N | I14: N | L14: N | M14: N | O14: N
B15: 46 | C15: Multi-Criteria Analysis of Sensor Reliability for Wearable Human Activity Recognition | D15: Yilin Dong | E15: N | G15: N | H15: N | L15: N | M15: N
B16: 87 | C16: Temporal-channel convolution with self-attention network for human activity recognition using wearable sensors | D16: Ehab Essa | E16: N | G16: N | H16: N | J16: N | L16: N | M16: N
B17: 13 | C17: Matched Filter Interpretation of CNN Classifiers with Application to HAR | D17: Mohammed M. Farag | E17: N | G17: N | H17: N | I17: N | J17: N
B18: 14 | C18: AccNet24: A deep learning framework for classifying 24-hour activity behaviours from wrist-worn accelerometer data under free-living environments | D18: Vahid Farrahi | G18: N | I18: N
B19: 85 | C19: A Comparative Study on Fitness Activity Recognition | D19: Igor Lopes de Faria | E19: N | F19: N | G19: N | I19: N | N19: N
B20: 7 | C20: Improving Activity Recognition while Reducing Misclassification of Unknown Activities | D20: Andrea Fasciglione | E20: N | G20: N | H20: N | L20: N | M20: N | N20: N | O20: N
B21: 152 | C21: Modelling time-series data generation with diffusion models for triaxial data | D21: Francisco M. Garcia-Moreno | E21: N | G21: N | H21: N | I21: N | J21: N | O21: N
B22: 15 | C22: How Accurately Can Your Wrist Device Recognize Daily Activities and Detect Falls? | D22: Martin Gjoreski | G22: N | H22: N | J22: N | O22: N
B23: 31 | C23: Reducing the Impact of Sensor Orientation Variability in Human Activity Recognition Using a Consistent Reference System | D23: Manuel Gil-Martín | E23: N | G23: N | H23: N | J23: N | O23: N
B24: 88 | C24: Towards Learning Discrete Representations via Self-Supervision for Wearables-Based Human Activity Recognition | D24: Harish Haresamudram | G24: N | H24: N | I24: N | J24: N
B25: 76 | C25: Deep Learning Approach for Complex Activity Recognition using Heterogeneous Sensors from Wearable Device | D25: Narit Hnoohom | G25: N | H25: N | I25: N | J25: N
B26: 61 | C26: Activity Recognition with Wristband Based on Histogram and Bayesian Classifiers | D26: Yi-Cong Huang | E26: N | F26: N | G26: N | H26: N | I26: N | J26: N | N26: N | O26: N | P26: N
B27: 37 | C27: A Comprehensive Analysis on Wearable Acceleration Sensors in Human Activity Recognition | D27: Majid Janidarmian | F27: N | G27: N | H27: N | O27: N
B28: 79 | C28: Topological persistence guided knowledge distillation for wearable sensor data | D28: Eun Som Jeon | G28: N | H28: N | I28: N | J28: N | K28: N
B29: 105 | C29: Deep Neural Networks for Time Series Classification in Human Activity Recognition | D29: Shreehar Joshi | E29: N | G29: N | H29: N | I29: N | J29: N
B30: 43 | C30: Rich learning representations for human activity recognition: How to empower deep feature learning for biological time series | D30: Ria Kanjilal | G30: N | H30: N | I30: N | M30: N | O30: N
B31: 58 | C31: A general framework for sensor-based human activity recognition | D31: Lukas Köping | G31: N | H31: N | I31: N | J31: N | N31: N | O31: N | P31: N
B32: 62 | C32: A Deep Learning-Based Semantic Segmentation Model Using MCNN and Attention Layer for Human Activity Recognition | D32: Sang-hyub Lee | G32: N | H32: N | N32: N
B33: 115 | C33: Accelerometer Dense Trajectories for Activity Recognition and People Identification | D33: Roberto Leyva | E33: N | F33: N | G33: N | H33: N | I33: N | J33: N | K33: N | L33: N | M33: N
B34: 112 | C34: Human activity recognition based on triaxial accelerometer using multi-feature weighted ensemble | D34: QingNan Li | E34: N | G34: N | H34: N | I34: N | N34: N | O34: N
B35: 103 | C35: Human Activity Recognition in Free Living Using a Wearable Sensor: A Two-Stage Approach | D35: Tianhui Li | E35: N | G35: N | H35: N | N35: N
B36: 142 | C36: Frequency-Aware Masked Autoencoders for Human Activity Recognition using Accelerometers | D36: Niels R. Lorenzen | G36: N | H36: N | I36: N | J36: N | O36: N
B37: 98 | C37: Research on human activity recognition based on active learning | D37: Rong Liu | E37: N | F37: N | G37: N | H37: N | J37: N | K37: N | L37: N | M37: N | O37: N
B38: 102 | C38: MFE-HAR: multiscale feature engineering for human activity recognitionusing wearable sensors | D38: Jianchao Lu | E38: N | G38: N | H38: N | J38: N | P38: N
B39: 51 | C39: Robust Single Accelerometer-Based Activity Recognition Using Modified Recurrence Plot | D39: Jianjie Lu | E39: N | G39: N | H39: N | I39: N | J39: N | M39: N | O39: N
B40: 150 | C40: A two-stage multi-branch fusion model for human activity recognition based on sensor data transformed by gramian angular difference field | D40: Limeng Lu | E40: N | H40: N | I40: N | P40: N
B41: 97 | C41: Wearable Computing for Internet of Things: A Discriminant Approach for Human Activity Recognition | D41: Wei Lu | G41: N | H41: N | J41: N
B42: 130 | C42: Data augmentation for Human Activity Recognition with Generative Adversarial Networks | D42: Marcos Lupion | H42: N | O42: N
B43: 41 | C43: Smart-Wearable Sensors and CNN-BiGRU Model: A Powerful Combination for Human Activity Recognition | D43: Hazma Ali Imran | E43: N | F43: N | G43: N | H43: N
B44: 63 | C44: Age Differences in Estimating Physical Activity by Wrist Accelerometry Using Machine Learning | D44: Mamoun T. Mardini | G44: N | H44: N | N44: N | O44: N
B45: 78 | C45: User-Independent Recognition of Sports Activities From a Single Wrist-Worn Accelerometer: A Template-Matching-Based Approach | D45: Jenny Margarito | H45: N | I45: N | N45: N | O45: N
B46: 47 | C46: An Activity Recognition Framework Deploying the Random Forest Classifier and A Single Optical Heart Rate Monitoring and Triaxial Accelerometer Wrist-Band | D46: Saeed Mehrang | N46: N
B47: 54 | C47: Sensor-based Complex Human Activity Recognition from Smartwatch Data using Hybrid Deep Learning Network | D47: Sakorn Mekruksavanich | G47: N | J47: N | M47: N
B48: 124 | C48: RNN-based deep learning for physical activity recognition using smartwatch sensors: A case study of simple and complex activity recognition | D48: Sakron Mekruksavanich | G48: N | H48: N | J48: N
B49: 77 | C49: Recognizing and Understanding Sport Activities Based on Wearable Sensor Signals Using Deep Residual Network | D49: Sakorn Mekruksavanich | E49: N | F49: N | G49: N | H49: N | J49: N | K49: N | L49: N | O49: N
B50: 107 | C50: Efficient Recognition of Complex Human Activities Based on Smartwatch Sensors Using Deep Pyramidal Residual Network | D50: Sakorn Mekruksavanich | G50: N | H50: N | J50: N | O50: N | P50: N
B51: 104 | C51: Deep Learning Networks for Complex Activity Recognition Based on Wrist-Worn Sensor | D51: Sakorn Mekruksavanich | E51: N | G51: N | H51: N
B52: 139 | C52: Effect of Sliding Window Sizes on Sensor-Based Human Activity Recognition Using Smartwatch Sensors and Deep Learning Approaches | D52: Sakorn Mekruksavanich | G52: N | H52: N | I52: N | J52: N | O52: N | P52: N
B53: 143 | C53: A Deep Hybrid Neural Network for Efficient Human Activity Recognition Based on Accelerometer Data from Wristband | D53: Sakorn Mekruksavanich | F53: N | G53: N | H53: N | J53: N
B54: 108 | C54: Evaluating the Impact of a Two-Stage Multivariate Data Cleansing Approach to Improve to the Performance of Machine Learning Classifiers: A Case Study in Human Activity Recognition | D54: Dionicio Neira-Rodado | G54: N | J54: N | K54: N
B55: 106 | C55: Design and assessment of the data analysis process for a wrist-worn smart object to detect atomic activities in the smart home | D55: Qin Ni | E55: N | F55: N | G55: N | N55: N
B56: 149 | C56: Language of actions: A generative model for activity recognition and next move prediction from motion sensors | D56: Hasan Ogul | E56: N | H56: N | J56: N | L56: N | M56: N | O56: N
B57: 35 | C57: Building robust models for Human Activity Recognition from raw accelerometers data using Gated Recurrent Units and Long Short Term Memory Neural Networks | D57: Jeremiah Okai | H57: N | I57: N | M57: N | O57: N
B58: 70 | C58: An Approach towards Position-Independent Human Activity Recognition Model based on Wearable Accelerometer Sensor | D58: Naima Qamar | E58: N | G58: N | H58: N | I58: N | O58: N
B59: 57 | C59: A Transformer Based Approach for Activity Detection | D59: Gulshan Sharma | E59: N | G59: N | H59: N | I59: N | J59: N | K59: N | M59: N | P59: N
B60: 68 | C60: An adaptive time window method for human activity recognition | D60: Zhang Sheng | H60: N | I60: N | J60: N | K60: N | N60: N
B61: 121 | C61: Mobile sensor based human activity recognition: distinguishing of challenging activities by applying long short-term memory deep learning modified by residual network concept | D61: Seyed Vahab Shojaedini | E61: N | G61: N | H61: N | I61: N | J61: N | P61: N
B62: 140 | C62: Transportation Mode Recognition Based on Low-Rate Acceleration and Location Signals With an Attention-Based Multiple-Instance Learning Network | D62: Christos Siargkas | E62: N | G62: N | H62: N | I62: N | J62: N | M62: N | O62: N
B63: 114 | C63: Improving the classification accuracy of streaming data using SAX similarity features | D63: Pekka Siirtola | G63: N | H63: N | N63: N | O63: N | P63: N
B64: 93 | C64: Smart Devices are Different: Assessing and Mitigating Mobile Sensing Heterogeneities for Activity Recognition | D64: Allan Stisen | G64: N | H64: N | O64: N
B65: 136 | C65: Ngram time series model to predict activity type and energy cost from wrist, hip and ankle accelerometers: implications of age | D65: Scott J Strath | F65: N | G65: N | H65: N | L65: N | M65: N | N65: N | O65: N
B66: 74 | C66: CapsGaNet: Deep Neural Network Based on Capsule and GRU for Human Activity Recognition | D66: Xiaojie Sun | G66: N | H66: N | N66: N
B67: 49 | C67: On-body localization of wearable devices: An investigation of position-aware activity recognition | D67: Timo Sztyler | G67: N | H67: N | O67: N
B68: 100 | C68: Position-aware activity recognition with wearable devices | D68: Timo Sztyler | G68: N | H68: N | I68: N | O68: N
B69: 141 | C69: Quantum-based Gated Recurrent Units for Multiclass Classification to Monitor Daily Living Activities for Early Disease Detection | D69: Bao-Nhi Dang Tran | E69: N | G69: N | H69: N | J69: N | K69: N
B70: 18 | C70: An Improved Activity Recognition Method Based on Smart Watch Data | D70: Dengpan Tian | G70: N | H70: N | I70: N | J70: N | N70: N | P70: N
B71: 48 | C71: Selective Ensemble Based on Extreme Learning Machine for Sensor-Based Human Activity Recognition | D71: Yiming Tian | H71: N | N71: N
B72: 72 | C72: A Novel Sensor-Based Human Activity Recognition Method Based on Hybrid Feature Selection and Combinational Optimization | D72: Yiming Tian | H72: N | N72: N
B73: 92 | C73: Human activity recognition based on random forests | D73: Lu Xu | G73: N | H73: N | I73: N | J73: N | N73: N | O73: N
B74: 60 | C74: Activity Recognition Using One-Versus-All Strategy with Relief-F and Self-Adaptive Algorithm | D74: M. N Shah Zainudin | E74: N | F74: N | G74: N | H74: N | L74: N | O74: N
B75: 145 | C75: An enhanced dual inception-attention-BiGRU-attention model integrating wavelet transform for wearable sensor-based human activity recognition | D75: Xingao Zhang | H75: N | I75: N | L75: N | M75: N
B76: 45 | C76: Human Activity Recognition Based on Motion Sensor Using U-Net | D76: Yong Zhang | E76: N | G76: N | I76: N | K76: N
B77: 29 | C77: Comparison of Data Preprocessing Approaches for Applying Deep Learning to Human Activity Recognition in the Context of Industry 4.0 | D77: Xiaochen Zheng | E77: N | G77: N | H77: N | I77: N
B78: 113 | C78: A Human Activity Recognition Model Based on Wearable Sensor | D78: Fan Zhou | E78: N | F78: N | G78: N | H78: N | I78: N | J78: N | K78: N | M78: N | N78: N | O78: N | P78: N
A79: Personalized HAR | B79: 26 | C79: Personalized Activity Recognition with Deep Triplet Embeddings | D79: David Burns | G79: N | H79: N | I79: N | J79: N
B80: 122 | C80: Activity Recognition Using Community Data to Complement Small Amounts of Labeled Instances | D80: Enrique Garcia-Ceja | E80: N | G80: N | H80: N | J80: N | M80: N | O80: N
B81: 2 | C81: Classifier Personalization for Activity Recognition Using Wrist Accelerometers | D81: Andrea Mannini
B82: 95 | C82: Smartwatch based activity recognition using active learning | D82: Farhad Shahmohammadi | G82: N | H82: N | I82: N | M82: N | N82: N | O82: N
B83: 110 | C83: From Lab to Real World: Assessing the Effectiveness of Human Activity Recognition and Optimization through Personalization | D83: Marija Stojchevska | E83: N | G83: N | H83: N | I83: N | J83: N | O83: N
B84: 67 | C84: A knowledge-light approach to personalised and open-ended human activity recognition | D84: Anjana Wijekoon | E84: N | G84: N | H84: N | J84: N
A85: Data Methodology (e.g., sensor location or device modality) | B85: 22 | C85: Smartwatch activity recognition feature comparison using ML.net | D85: Alexandru Alexan | G85: N | H85: N | J85: N | P85: N
B86: 80 | C86: Estimating Energy Expenditure Using Body-Worn Accelerometers: A Comparison of Methods, Sensors Number and Positioning | D86: Marco Altini | G86: N | M86: N | N86: N | O86: N
B87: 10 | C87: Human Activity Recognition: A Comparative Study to Assess the Contribution Level of Accelerometer, ECG, and PPG Signals | D87: Mahsa Sadat Afzali Arani | G87: N
B88: 96 | C88: Sensor Placement for Activity Detection Using Wearable Accelerometers | D88: Louis Atallah | E88: N | G88: N | N88: N | O88: N
B89: 120 | C89: Sensor positioning for activity recognition using wearable accelerometers | D89: Louis Atallah | I89: N | N89: N | O89: N
B90: 148 | C90: WEAR: An Outdoor Sports Dataset for Wearable and Egocentric Activity Recognition | D90: Marius Bock | H90: N | O90: N
B91: 17 | C91: Optimal Placement of Accelerometers for the Detection of Everyday Activities | D91: Ian Cleland | H91: N | N91: N | O91: N
B92: 154 | C92: Assessing the impact of body location on the accuracy of detecting daily activities with accelerometer data | D92: Xiangnan Dang | E92: N | G92: N | L92: N | M92: N | O92: N
B93: 116 | C93: The Effect of Sensor Placement and Number on Physical Activity Recognition and Energy Expenditure Estimation in Older Adults: Validation Study | D93: Anis Davoudi | G93: N | H93: N | N93: N | O93: N
B94: 109 | C94: Free-living Ambulatory Activity Classification: A Comparative Analysis of Wrist-worn, Insole-embedded, and Phone-embedded Sensors | D94: Ton T. H. Duong | G94: N | N94: N
B95: 34 | C95: Evaluating sensor placement and modality for activity recognition inactive games | D95: Natalie Jablonsky | G95: N | H95: N | N95: N
B96: 69 | C96: Analyzing Body Movements within the Laban Effort Framework Using a Single Accelerometer | D96: Basel Kikhia | N96: N
B97: 137 | C97: Activity recognition using a single accelerometer placed at the wrist or ankle | D97: Andrea Mannini | M97: N
B98: 101 | C98: Placement Effect of Motion Sensors for Human Activity Recognition using LSTM Network | D98: Sakorn Mekruksavanich | F98: N | G98: N | H98: N | I98: N | L98: N | M98: N
B99: 65 | C99: Evaluation of Smartphone and Smartwatch Accelerometer Data in Activity Classification | D99: Nguyen Canh Minh | G99: N | H99: N | I99: N | J99: N | M99: N | O99: N
B100: 55 | C100: Analysis of Optimal Sensor Positions for Activity Classification and Application on a Different Data Collection Scenario | D100: Natthapon Pannurat | G100: N | H100: N | I100: N | N100: N
...
